{
  "DmF_GE_BattleAfter_Text_001_b.bwav": "",
  "DmF_GE_BattleAfter_Text_002_b.bwav": "",
  "DmF_GE_BattleAfter_Text_004_b.bwav": "",
  "DmT_BC_MeetAgain_Text_000_b.bwav": "",
  "DmT_BC_MeetAgain_Text_001_b.bwav": "啊，你之前都去哪里了……",
  "DmT_BC_MeetAgain_Text_002_b.bwav": "你、你该不会是幽灵吧？",
  "DmT_BC_MeetAgain_Text_003_ab.bwav": "",
  "DmT_BC_MeetAgain_Text_003_b.bwav": "你的手怎么了……",
  "DmT_BC_MeetAgain_Text_004_ab.bwav": "",
  "DmT_BC_MeetAgain_Text_004_b.bwav": "你遭遇了什么……",
  "DmT_BC_MeetAgain_Text_005_b.bwav": "你会告诉我的吧。",
  "DmT_BZ_BossIn_Text_000_b.bwav": "林克。",
  "DmT_BZ_BossIn_Text_001_b.bwav": "我一直在等你过来。",
  "DmT_BZ_BossIn_Text_002_b.bwav": "林克，我啊……\n有个地方想让你看看。",
  "DmT_BZ_BossIn_Text_003_ab.bwav": "",
  "DmT_BZ_BossIn_Text_003_b.bwav": "怎么样？",
  "DmT_BZ_BossIn_Text_004_b.bwav": "曾经极尽荣华的海拉鲁城堡。",
  "DmT_BZ_BossIn_Text_005_b.bwav": "很怀念吧？",
  "DmT_BZ_BossIn_Text_006_b.bwav": "林克和我充满回忆的地方……",
  "DmT_BZ_BossIn_Text_007_b.bwav": "好好记住这片美景吧……",
  "DmT_BZ_BossIn_Text_008_b.bwav": "毕竟这会是你……",
  "DmT_BZ_BossIn_Text_009_b.bwav": "临终前最后欣赏的风景了……",
  "DmT_BZ_BossIn_Text_009_c.bwav": "",
  "DmT_BZ_BossIn_Text_009_d.bwav": "",
  "DmT_BZ_BossIn_Text_012_b.bwav": "被我的瘴气侵蚀，却幸免于难……\n而后屠戮我手下仆从的剑士……",
  "DmT_BZ_BossIn_Text_013_b.bwav": "那时候，你之所以能活下来……",
  "DmT_BZ_BossIn_Text_014_b.bwav": "是因为那条可悲的右臂的协助吗……",
  "DmT_BZ_BossIn_Text_015_b.bwav": "",
  "DmT_BZ_BossIn_Text_016_b.bwav": "无妨，\n难得续上了性命，也死到临头了……",
  "DmT_BZ_BossIn_Text_017_aab.bwav": "拿这小姑娘的样貌蛊惑你们，\n观察你们的反应，还真是妙不可言……",
  "DmT_BZ_BossIn_Text_017_ab.bwav": "但现在早已没那个必要了……",
  "DmT_BZ_BossIn_Text_017_b.bwav": "由我血肉所铸的木偶啊……\n去了结那小子的生命吧！",
  "DmT_BZ_BossIn_Text_020_b.bwav": "",
  "DmT_BZ_BossOut_Text_000_b.bwav": "",
  "DmT_BZ_BossOut_Text_001_b.bwav": "原来……\n并不只有……劳鲁那家伙的力量吗。",
  "DmT_BZ_BossOut_Text_002_b.bwav": "还是趁现在收拾干净好了。",
  "DmT_BZ_BossOut_Text_004_b.bwav": "",
  "DmT_BZ_BossOut_Text_005_b.bwav": "",
  "DmT_BZ_BossOut_Text_006_b.bwav": "",
  "DmT_BZ_BossOut_Text_007_b.bwav": "",
  "DmT_BZ_BossOut_Text_008_b.bwav": "林克！没事吧！？",
  "DmT_BZ_BossOut_Text_009_b.bwav": "秘石的持有者吗……",
  "DmT_BZ_BossOut_Text_010_b.bwav": "你到底是谁！",
  "DmT_BZ_BossOut_Text_011_c.bwav": "居然不认识我，那看来……\n那块石头并没有给你们神代的记忆啊……",
  "DmT_BZ_BossOut_Text_012_b.bwav": "我名为加侬多夫……",
  "DmT_BZ_BossOut_Text_013_b.bwav": "你们祖先所施加的愚蠢封印，\n不过是拖延些许时间……",
  "DmT_BZ_BossOut_Text_014_c.bwav": "让你们见识一下，过去的模样……\n我的力量回复之时……那再次降临的魔之世界！",
  "DmT_BZ_GoBackBC_Text_000_b.bwav": "",
  "DmT_BZ_GoBackBC_Text_001_b.bwav": "",
  "DmT_BZ_GoBackBC_Text_002_b.bwav": "",
  "DmT_BZ_GoBackBC_Text_003_b.bwav": "",
  "DmT_BZ_GoBackBC_Text_004_b.bwav": "",
  "DmT_BZ_GoBackBC_Text_004_c.bwav": "用不了多久了。",
  "DmT_BZ_GoBackBC_Text_005_b.bwav": "",
  "DmT_BZ_GoBackBC_Text_006_b.bwav": "",
  "DmT_BZ_GoBackBC_Text_007_b.bwav": "",
  "DmT_BZ_GoBackBC_Text_008_b.bwav": "",
  "DmT_BZ_GoBackBC_Text_009_c.bwav": "当我恢复力量之时……",
  "DmT_BZ_GoBackBC_Text_010_b.bwav": "你们便将与这黑暗吞没的世界，\n一同迎来灭亡。",
  "DmT_BZ_GoBackBC_Text_011_b.bwav": "",
  "DmT_BZ_GoBackBC_Text_012_aab.bwav": "",
  "DmT_BZ_GoBackBC_Text_012_ab.bwav": "",
  "DmT_BZ_GoBackBC_Text_012_b.bwav": "先祖说的魔王……就是那家伙！？\n刚刚那些都是真的吗！？",
  "DmT_BZ_GoBackBC_Text_013_b.bwav": "肯定没错，那就是\n在遥远的过去险些毁灭世界的魔王……",
  "DmT_BZ_GoBackBC_Text_014_b.bwav": "加侬多夫！",
  "DmT_BZ_GoBackBC_Text_015_b.bwav": "他现在苏醒了，又要再次……",
  "DmT_BZ_GoBackBC_Text_016_b.bwav": "这可不好笑鼓咯！\n要是真这样，那全都完蛋了鼓咯！",
  "DmT_BZ_GoBackBC_Text_017_b.bwav": "不……他应该还没有回复完全，\n毕竟他刚刚放过了我们就消失了。",
  "DmT_BZ_GoBackBC_Text_018_b.bwav": "暂且回到监视堡垒，研究一下对策如何？",
  "DmT_BZ_GoBackBC_Text_019_b.bwav": "林克，你也过来吧。",
  "DmT_GA_LastBossTransform_Text_000_ab.bwav": "",
  "DmT_GA_LastBossTransform_Text_000_b.bwav": "好久没有此等感觉了。",
  "DmT_GA_LastBossTransform_Text_001_b.bwav": "血液翻涌，骨肉雀跃……\n身体的每一处都在渴求解放更大的力量……",
  "DmT_GA_LastBossTransform_Text_003_d.bwav": "",
  "DmT_GA_LastBossTransform_Text_004_ab.bwav": "",
  "DmT_GA_LastBossTransform_Text_004_b.bwav": "",
  "DmT_GA_LastBossTransform_Text_005_b.bwav": "是时候宣告终结了。",
  "DmT_GA_LastBossTransform_Text_006_b.bwav": "这次，光凭你那手臂可无济于事。",
  "DmT_GE_Awake_Text_022_c.bwav": "与林克共同战斗，是我的宿命……",
  "DmT_GE_Awake_Text_023_b.bwav": "",
  "DmT_GE_Awake_Text_024_c.bwav": "身为族长的职责，身为贤者的宿命，\n以及和林克并肩作战……",
  "DmT_GE_Awake_Text_025_b.bwav": "有趣！",
  "DmT_GE_Awake_Text_026_b.bwav": "我不会让什么魔王对这个世界为所欲为。",
  "DmT_GE_Awake_Text_027_b.bwav": "这秘石，就由我继承！",
  "DmT_GE_Awake_Text_030_bb.bwav": "我乃雷之贤者！\n看吧！这就是贤者之力！",
  "DmT_GE_Awake_Text_031_b.bwav": "",
  "DmT_GE_Awake_Text_032_b.bwav": "林克……把手给我。",
  "DmT_GE_Awake_Text_033_b.bwav": "我以雷之贤者露珠之名起誓，\n将与你共同奋战到底。",
  "DmT_GE_Awake_Text_034_b.bwav": "收下便是！这是誓约的证明！",
  "DmT_GE_Awake_Text_037_c.bwav": "有了这枚戒指，\n我的力量会时刻与林克同在。",
  "DmT_GE_Awake_Text_038_c.bwav": "这下终于能向你报答恩情了。",
  "DmT_GE_Awake_Text_039_c.bwav": "那么，我们回小镇去吧。",
  "DmT_GE_BossIn_Text_000_ab.bwav": "",
  "DmT_GE_BossIn_Text_000_b.bwav": "快看，林克！\n沙尘就是那家伙搞出来的！",
  "DmT_GE_BossIn_Text_001_b.bwav": "它就是一切的元凶！",
  "DmT_GE_BossIn_Text_003_b.bwav": "林克！\n助我一臂之力吧！",
  "DmT_GE_KaraBazaAfter_Text_000_b.bwav": "碧优拉，\n能坚持到我们来，真是辛苦你了。",
  "DmT_GE_KaraBazaAfter_Text_001_b.bwav": "这次能确认雷击对吉波得有效，\n真是个大收获啊。",
  "DmT_GE_KaraBazaAfter_Text_002_b.bwav": "",
  "DmT_GE_KaraBazaAfter_Text_005_b.bwav": "",
  "DmT_GE_KaraBazaAfter_Text_006_b.bwav": "塞、塞尔达！？",
  "DmT_GE_KaraBazaAfter_Text_007_aab.bwav": "",
  "DmT_GE_KaraBazaAfter_Text_007_b.bwav": "",
  "DmT_GE_KaraBazaAfter_Text_009_b.bwav": "那个……究竟是！？",
  "DmT_GE_KaraBazaAfter_Text_010_b.bwav": "是格鲁德小镇的方向！",
  "DmT_GE_KaraBazaAfter_Text_010_d.bwav": "塞尔达！",
  "DmT_GE_KaraBazaAfter_Text_011_ad.bwav": "格鲁德小镇那边出现了龙卷风……\n往那儿去的塞尔达也消失了……",
  "DmT_GE_KaraBazaAfter_Text_011_c.bwav": "碧优拉！快回到镇上！",
  "DmT_GE_KaraBazaAfter_Text_012_b.bwav": "",
  "DmT_GE_KaraBazaAfter_Text_013_c.bwav": "林克，我们先走一步。",
  "DmT_GE_KaraBazaAfter_Text_015_b.bwav": "待会儿在镇上会合吧！",
  "DmT_GE_MeetAgain_Text_000_b.bwav": "",
  "DmT_GE_MeetAgain_Text_001_b.bwav": "",
  "DmT_GE_MeetAgain_Text_002_b.bwav": "",
  "DmT_GE_MeetAgain_Text_003_b.bwav": "",
  "DmT_GE_MeetAgain_Text_004_b.bwav": "没中啊……",
  "DmT_GE_MeetAgain_Text_005_b.bwav": "现在这样……又会保护不了大家……",
  "DmT_GE_MeetAgain_Text_006_b.bwav": "",
  "DmT_GE_MeetAgain_Text_007_b.bwav": "林克！？",
  "DmT_GE_MeetAgain_Text_008_b.bwav": "……真让人吃惊。",
  "DmT_GE_MeetAgain_Text_009_b.bwav": "没想到会在这种地方见到你……",
  "DmT_GE_MeetAgain_Text_010_b.bwav": "……你总是突然出现呢。",
  "DmT_GE_StoneGet_Text_000_b.bwav": "",
  "DmT_GE_StoneGet_Text_000_c.bwav": "",
  "DmT_GE_StoneGet_Text_001_b.bwav": "",
  "DmT_GE_StoneGet_Text_002_b.bwav": "",
  "DmT_GE_StoneMind_Text_000_b.bwav": "后代啊……\n继承吾血之人，露珠……",
  "DmT_GE_StoneMind_Text_001_ab.bwav": "",
  "DmT_GE_StoneMind_Text_001_b.bwav": "就是那声音……",
  "DmT_GE_StoneMind_Text_002_b.bwav": "一直在和我们说话……？",
  "DmT_GE_StoneMind_Text_003_c.bwav": "吾乃汝遥远之祖先。",
  "DmT_GE_StoneMind_Text_004_b.bwav": "吾侍奉初代海拉鲁国王，身为格鲁德族战士，\n亦是司雷之贤者……",
  "DmT_GE_StoneMind_Text_005_b.bwav": "汝释放强雷，战斗自如，实乃出色。\n不愧为吾之后代……格鲁德之骄傲。",
  "DmT_GE_StoneMind_Text_006_b.bwav": "那即是沙尘之元凶，\n乃魔王所遣之怪物。",
  "DmT_GE_StoneMind_Text_007_b.bwav": "其目的在于阻止汝得到\n先前所触之石——秘石。",
  "DmT_GE_StoneMind_Text_008_b.bwav": "魔王……？秘石……？",
  "DmT_GE_StoneMind_Text_009_b.bwav": "诚然……此二者将同汝密不可分。",
  "DmT_GE_StoneMind_Text_010_c.bwav": "因此，愿汝悉心倾听……",
  "DmT_GE_StoneMind_Text_012_b.bwav": "名曰封印战争之战，\n及吾等一族之宿命……",
  "DmT_GO_Awake_Text_003_c.bwav": "与林克共同战斗，是我的命运鼓咯？",
  "DmT_GO_Awake_Text_004_b.bwav": "",
  "DmT_GO_Awake_Text_005_c.bwav": "希望我继承这个……认真的吗……？",
  "DmT_GO_Awake_Text_006_b.bwav": "我不如先祖大人们一样杰出……",
  "DmT_GO_Awake_Text_007_b.bwav": "但是，如果现在迷茫的话，\n会没脸面对大家的鼓咯。",
  "DmT_GO_Awake_Text_008_b.bwav": "我不能一直任性下去……我要证明自己鼓咯！",
  "DmT_GO_Awake_Text_011_bb.bwav": "我是火之贤者！\n看！这就是贤者之力鼓咯！",
  "DmT_GO_Awake_Text_012_b.bwav": "",
  "DmT_GO_Awake_Text_013_b.bwav": "林克……把手伸出来鼓咯！",
  "DmT_GO_Awake_Text_013_c.bwav": "",
  "DmT_GO_Awake_Text_014_b.bwav": "我以火之贤者阿沅之名发誓，\n和你一起战斗到底！",
  "DmT_GO_Awake_Text_015_b.bwav": "收下吧！这就是誓言的证明鼓咯！",
  "DmT_GO_Awake_Text_018_c.bwav": "有了这枚戒指，\n我的力量会一直伴随林克鼓咯。",
  "DmT_GO_Awake_Text_019_c.bwav": "为了能堂堂正正站在你的身边，我会越来越强鼓咯！",
  "DmT_GO_Awake_Text_020_b.bwav": "走吧，我们回去鼓咯！",
  "DmT_GO_BossIn_Text_000_b.bwav": "塞尔达殿下在哪里鼓咯！？",
  "DmT_GO_BossIn_Text_001_b.bwav": "那、那是……",
  "DmT_GO_BossIn_Text_002_b.bwav": "是、是怪物鼓咯！",
  "DmT_GO_BossIn_Text_003_b.bwav": "",
  "DmT_GO_BossIn_Text_004_b.bwav": "不好了鼓咯！塞、塞尔达殿下在怪物体内！？",
  "DmT_GO_BossIn_Text_005_b.bwav": "林克，干掉它拯救塞尔达殿下鼓咯！！",
  "DmT_GO_MeetAgain_Text_002_b.bwav": "又在诋毁可口岩吗鼓咯？",
  "DmT_GO_MeetAgain_Text_002_c.bwav": "",
  "DmT_GO_MeetAgain_Text_003_b.bwav": "可口岩没有任何问题鼓咯。",
  "DmT_GO_MeetAgain_Text_004_b.bwav": "别说什么傻话了，\n你也过来这边鼓咯。",
  "DmT_GO_MeetAgain_Text_007_b.bwav": "",
  "DmT_GO_MeetAgain_Text_008_b.bwav": "你是……",
  "DmT_GO_MiddleBossIn_Text_000_b.bwav": "好像就是这里鼓咯……",
  "DmT_GO_MiddleBossIn_Text_002_c.bwav": "当时我来调查死亡之山，\n塞尔达殿下就站在这里鼓咯。",
  "DmT_GO_MiddleBossIn_Text_002_d.bwav": "然后，塞尔达殿下就给我戴上了面罩……\n再然后就……我想想……",
  "DmT_GO_MiddleBossIn_Text_002_e.bwav": "不行鼓咯……想不起来了，\n从这里开始就没有记忆了鼓咯……",
  "DmT_GO_MiddleBossIn_Text_003_b.bwav": "",
  "DmT_GO_MiddleBossIn_Text_003_c.bwav": "",
  "DmT_GO_MiddleBossIn_Text_004_b.bwav": "",
  "DmT_GO_MiddleBossIn_Text_005_c.bwav": "找到了！塞尔达殿下！",
  "DmT_GO_MiddleBossIn_Text_005_d.bwav": "塞尔达殿下，我有话和你说鼓咯！\n那边很危险，快来这边一起……",
  "DmT_GO_MiddleBossIn_Text_006_b.bwav": "",
  "DmT_GO_StoneGet_Text_000_b.bwav": "",
  "DmT_GO_StoneGet_Text_001_b.bwav": "",
  "DmT_GO_StoneGet_Text_002_b.bwav": "",
  "DmT_GO_StoneGet_Text_003_b.bwav": "",
  "DmT_GO_StoneMind_Text_000_b.bwav": "后代啊……\n继承吾血之人，阿沅……",
  "DmT_GO_StoneMind_Text_001_b.bwav": "那声音……",
  "DmT_GO_StoneMind_Text_002_b.bwav": "是一直和我们说话的人鼓咯……？",
  "DmT_GO_StoneMind_Text_003_c.bwav": "吾乃汝遥远之祖先。",
  "DmT_GO_StoneMind_Text_004_b.bwav": "吾侍奉初代海拉鲁国王，身为鼓隆族战士，\n亦是司火之贤者……",
  "DmT_GO_StoneMind_Text_005_b.bwav": "汝以身为剑，身姿豪迈，实乃出色。\n不愧为吾之后代……鼓隆之骄傲。",
  "DmT_GO_StoneMind_Text_006_b.bwav": "那即是惑众岩石之元凶，\n乃魔王所遣之怪物。",
  "DmT_GO_StoneMind_Text_007_b.bwav": "其目的在于阻止汝得到\n先前所触之石——秘石。",
  "DmT_GO_StoneMind_Text_008_b.bwav": "魔王和……秘石……？",
  "DmT_GO_StoneMind_Text_009_b.bwav": "诚然……想必汝是初次听闻。",
  "DmT_GO_StoneMind_Text_010_c.bwav": "正因如此，愿汝听吾讲述……",
  "DmT_GO_StoneMind_Text_012_b.bwav": "名曰封印战争之战，\n及吾等一族之天命！",
  "DmT_OP_GanonWakeUp_Text_000_b.bwav": "那是……",
  "DmT_OP_GanonWakeUp_Text_001_b.bwav": "",
  "DmT_OP_GanonWakeUp_Text_001_c.bwav": "",
  "DmT_OP_GanonWakeUp_Text_002_b.bwav": "",
  "DmT_OP_GanonWakeUp_Text_003_b.bwav": "",
  "DmT_OP_GanonWakeUp_Text_004_b.bwav": "",
  "DmT_OP_GanonWakeUp_Text_005_b.bwav": "林克！！",
  "DmT_OP_GanonWakeUp_Text_006_b.bwav": "……那就是驱魔之剑？\n为我瘴气所破之刃，一无是处。",
  "DmT_OP_GanonWakeUp_Text_007_b.bwav": "塞尔达……",
  "DmT_OP_GanonWakeUp_Text_007_c.bwav": "",
  "DmT_OP_GanonWakeUp_Text_008_b.bwav": "驱魔之剑的持有者……",
  "DmT_OP_GanonWakeUp_Text_009_b.bwav": "林克……",
  "DmT_OP_GanonWakeUp_Text_010_b.bwav": "劳鲁口中的希望……",
  "DmT_OP_GanonWakeUp_Text_010_bb.bwav": "也不过如此……",
  "DmT_OP_GanonWakeUp_Text_010_c.bwav": "你为什么……知道我们的名字……？",
  "DmT_OP_GanonWakeUp_Text_011_b.bwav": "",
  "DmT_OP_GanonWakeUp_Text_012_b.bwav": "林克！",
  "DmT_OP_GanonWakeUp_Text_012_c.bwav": "",
  "DmT_OP_GanonWakeUp_Text_013_b.bwav": "",
  "DmT_RT_Awake_Text_017_c.bwav": "与林克一同战斗是我的使命？",
  "DmT_RT_Awake_Text_018_b.bwav": "",
  "DmT_RT_Awake_Text_019_b.bwav": "林克！我真是太高兴了！！",
  "DmT_RT_Awake_Text_020_b.bwav": "先祖大人将重要的使命托付于我，\n而且还是让我和林克并肩作战！",
  "DmT_RT_Awake_Text_021_b.bwav": "如果现在什么都不做，\n世界就会变得一团糟吧？",
  "DmT_RT_Awake_Text_022_b.bwav": "我不会让这种事情发生的……\n我很乐意继承这个秘石！",
  "DmT_RT_Awake_Text_025_bb.bwav": "我是风之贤者！\n看好了！这就是贤者之力！",
  "DmT_RT_Awake_Text_026_b.bwav": "",
  "DmT_RT_Awake_Text_027_b.bwav": "林克……把手伸出来吧！",
  "DmT_RT_Awake_Text_028_b.bwav": "我以风之贤者丘栗之名，\n发誓与你并肩作战。",
  "DmT_RT_Awake_Text_029_b.bwav": "收下它吧！这就是证明！！",
  "DmT_RT_Awake_Text_032_bb.bwav": "",
  "DmT_RT_Awake_Text_032_c.bwav": "有了这枚戒指，\n我的力量将会一直与林克你同在。",
  "DmT_RT_Awake_Text_033_b.bwav": "好～！赶紧回到村里向爸爸他们报告！",
  "DmT_RT_BossIn_Text_002_b.bwav": "",
  "DmT_RT_BossIn_Text_003_b.bwav": "",
  "DmT_RT_BossIn_Text_005_b.bwav": "",
  "DmT_RT_BossIn_Text_007_b.bwav": "",
  "DmT_RT_BossIn_Text_009_b.bwav": "出发吧，林克！",
  "DmT_RT_BossIn_Text_011_c.bwav": "就是那家伙用暴风雪袭击村子的吧！",
  "DmT_RT_BossIn_Text_012_c.bwav": "我绝对饶不了它！",
  "DmT_RT_StoneGet_Text_000_b.bwav": "",
  "DmT_RT_StoneGet_Text_000_c.bwav": "",
  "DmT_RT_StoneGet_Text_000_d.bwav": "",
  "DmT_RT_StoneGet_Text_001_b.bwav": "",
  "DmT_RT_StoneMind_Text_000_b.bwav": "后代啊……\n继承吾血之人，丘栗……",
  "DmT_RT_StoneMind_Text_001_b.bwav": "那声音……",
  "DmT_RT_StoneMind_Text_002_b.bwav": "是之前一直和我们说话的人……？",
  "DmT_RT_StoneMind_Text_003_c.bwav": "吾乃汝遥远之祖先。",
  "DmT_RT_StoneMind_Text_004_b.bwav": "吾侍奉初代海拉鲁国王，身为利特族战士，\n亦是司风之贤者……",
  "DmT_RT_StoneMind_Text_005_b.bwav": "汝掌控风力，战斗自如，实乃出色。\n不愧为吾之后代……利特之骄傲。",
  "DmT_RT_StoneMind_Text_006_c.bwav": "那即是袭扰村庄暴风雪之元凶，\n乃魔王所遣之怪物。",
  "DmT_RT_StoneMind_Text_007_b.bwav": "其目的在于阻止汝得到\n先前所触之石——秘石。",
  "DmT_RT_StoneMind_Text_008_b.bwav": "魔王……？秘石……？",
  "DmT_RT_StoneMind_Text_009_b.bwav": "诚然……想必汝有诸多疑惑。",
  "DmT_RT_StoneMind_Text_010_b.bwav": "因此，愿汝事先知晓……",
  "DmT_RT_StoneMind_Text_012_b.bwav": "名曰封印战争之战，\n及吾等一族之使命！",
  "DmT_SY_BloodyMoonDarkZelda_Text_002_b.bwav": "当染红的月亮照耀大地之时……",
  "DmT_SY_BloodyMoonDarkZelda_Text_003_c.bwav": "怪物的灵魂将获得肉体得以复活……",
  "DmT_SY_BloodyMoonDarkZelda_Text_004_b.bwav": "再次席卷这片大地……",
  "DmT_SY_BloodyMoonFirst_Text_000_b.bwav": "月亮啊……\n被染红的月亮啊……",
  "DmT_SY_BloodyMoonFirst_Text_001_b.bwav": "当你的光辉照耀这片大地之时……",
  "DmT_SY_BloodyMoonFirst_Text_002_b.bwav": "怪物们的灵魂将再次获得肉体得以复活……",
  "DmT_SY_BloodyMoonFirst_Text_003_b.bwav": "宛如远古大战一般……",
  "DmT_SY_BloodyMoonFirst_Text_004_b.bwav": "再次席卷这片大地……",
  "DmT_ZE_Birth_Text_000_b.bwav": "索尼娅大人！\n索尼娅大人！",
  "DmT_ZE_Birth_Text_001_b.bwav": "终于……！",
  "DmT_ZE_Birth_Text_002_b.bwav": "它终于归我了！！",
  "DmT_ZE_Birth_Text_003_b.bwav": "啊……\n我感觉充满了力量……！",
  "DmT_ZE_Birth_Text_004_b.bwav": "",
  "DmT_ZE_Birth_Text_005_b.bwav": "",
  "DmT_ZE_Birth_Text_006_c.bwav": "",
  "DmT_ZE_Birth_Text_006_d.bwav": "",
  "DmT_ZE_Birth_Text_006_e.bwav": "",
  "DmT_ZE_Birth_Text_006_f.bwav": "",
  "DmT_ZE_Birth_Text_006_g.bwav": "",
  "DmT_ZE_Birth_Text_006_h.bwav": "",
  "DmT_ZE_Birth_Text_007_bb.bwav": "",
  "DmT_ZE_Birth_Text_007_c.bwav": "",
  "DmT_ZE_Birth_Text_008_b.bwav": "",
  "DmT_ZE_Birth_Text_009_b.bwav": "",
  "DmT_ZE_Birth_Text_010_ac.bwav": "",
  "DmT_ZE_Birth_Text_010_c.bwav": "索尼娅……！",
  "DmT_ZE_Birth_Text_011_b.bwav": "已经太迟了，劳鲁……",
  "DmT_ZE_Birth_Text_012_b.bwav": "它已经是我的东西了！\n我会站在高处俯视你们……",
  "DmT_ZE_Birth_Text_013_b.bwav": "理所当然地独占这份神一般的力量！！",
  "DmT_ZE_Birth_Text_013_c.bwav": "",
  "DmT_ZE_Birth_Text_014_b.bwav": "这个女人就是你傲慢的牺牲品！！",
  "DmT_ZE_Birth_Text_015_b.bwav": "你就带着自以为能控制我的悔恨长辞吧，\n劳鲁！",
  "DmT_ZE_Birth_Text_016_ac.bwav": "",
  "DmT_ZE_Birth_Text_016_c.bwav": "加侬多夫！",
  "DmT_ZE_Birth_Text_017_b.bwav": "劳鲁大人！",
  "DmT_ZE_Birth_Text_017_c.bwav": "",
  "DmT_ZE_Birth_Text_018_b.bwav": "趁现在，快去救索尼娅大人！",
  "DmT_ZE_Birth_Text_019_b.bwav": "",
  "DmT_ZE_Birth_Text_020_b.bwav": "",
  "DmT_ZE_Birth_Text_021_b.bwav": "",
  "DmT_ZE_Birth_Text_022_b.bwav": "",
  "DmT_ZE_Birth_Text_023_b.bwav": "",
  "DmT_ZE_Birth_Text_024_b.bwav": "",
  "DmT_ZE_Birth_Text_024_c.bwav": "",
  "DmT_ZE_Birth_Text_024_cb.bwav": "",
  "DmT_ZE_Birth_Text_025_b.bwav": "",
  "DmT_ZE_Birth_Text_026_b.bwav": "",
  "DmT_ZE_Birth_Text_027_b.bwav": "",
  "DmT_ZE_LieServant_Text_000_b.bwav": "关于多次迟于赴约，",
  "DmT_ZE_LieServant_Text_001_b.bwav": "我们格鲁德一族",
  "DmT_ZE_LieServant_Text_002_b.bwav": "由衷感到抱歉。",
  "DmT_ZE_LieServant_Text_003_c.bwav": "我们衷心希望\n能够加入您的麾下。",
  "DmT_ZE_LieServant_Text_004_b.bwav": "很好，加侬多夫。\n我认同你们归顺于海拉鲁王国。",
  "DmT_ZE_LieServant_Text_005_b.bwav": "格鲁德一族100年一见的男性。",
  "DmT_ZE_LieServant_Text_006_b.bwav": "“生而为王”的勇敢男性，\n我们海拉鲁竟能迎来此等人才……",
  "DmT_ZE_LieServant_Text_007_b.bwav": "实在是太令人放心了。",
  "DmT_ZE_LieServant_Text_008_b.bwav": "这是我的荣幸。",
  "DmT_ZE_LieServant_Text_009_b.bwav": "曾经，左纳乌族从天而降的身姿\n就如神明一般……",
  "DmT_ZE_LieServant_Text_010_b.bwav": "可是陛下身为其后裔，\n却迎娶了一名海拉鲁族的姑娘……",
  "DmT_ZE_LieServant_Text_011_aab.bwav": "",
  "DmT_ZE_LieServant_Text_011_b.bwav": "跨越部落氏族的这种治世方式，",
  "DmT_ZE_LieServant_Text_012_b.bwav": "真是绝妙……",
  "DmT_ZE_LieServant_Text_013_b.bwav": "",
  "DmT_ZE_LieServant_Text_014_b.bwav": "但是如此高洁的左纳乌族竟走向灭亡，\n只剩下陛下和陛下的姐姐……",
  "DmT_ZE_LieServant_Text_015_b.bwav": "真是令人感到遗憾……",
  "DmT_ZE_LieServant_Text_016_b.bwav": "就算我灭亡了，现在的安宁也不会分崩离析，\n我们的国家也还能长久发展。",
  "DmT_ZE_LieServant_Text_017_b.bwav": "",
  "DmT_ZE_LieServant_Text_019_b.bwav": "此番辛苦你了。\n我对你很期待，加侬多夫！",
  "DmT_ZE_LieServant_Text_020_b.bwav": "你退下吧。",
  "DmT_ZE_LieServant_Text_021_b.bwav": "遵命。",
  "DmT_ZE_LieServant_Text_022_b.bwav": "劳鲁大人……",
  "DmT_ZE_LieServant_Text_023_b.bwav": "我从那个人身上感觉到了深不见底的野心。",
  "DmT_ZE_LieServant_Text_024_b.bwav": "而且他的名字……\n令我生出不祥的预感……",
  "DmT_ZE_LieServant_Text_025_c.bwav": "我看得出他那邪恶的本性。",
  "DmT_ZE_LieServant_Text_026_c.bwav": "但是正因如此，我才要让他在我身边得以监视。",
  "DmT_ZE_LieServant_Text_027_c.bwav": "",
  "DmT_ZE_LieServant_Text_028_d.bwav": "你不用担心。",
  "DmT_ZE_LieServant_Text_029_b.bwav": "我明白了……",
  "DmT_ZE_Meet_Text_002_bbb.bwav": "……嗯？",
  "DmT_ZE_Meet_Text_002_bd.bwav": "哎呀！不好！",
  "DmT_ZE_Meet_Text_002_c.bwav": "",
  "DmT_ZE_Meet_Text_003_b.bwav": "",
  "DmT_ZE_Meet_Text_004_b.bwav": "",
  "DmT_ZE_Meet_Text_005_b.bwav": "",
  "DmT_ZE_Meet_Text_005_c.bwav": "",
  "DmT_ZE_Meet_Text_006_b.bwav": "",
  "DmT_ZE_Meet_Text_007_b.bwav": "",
  "DmT_ZE_Meet_Text_008_b.bwav": "",
  "DmT_ZE_Meet_Text_009_b.bwav": "",
  "DmT_ZE_Meet_Text_010_b.bwav": "",
  "DmT_ZE_Meet_Text_011_b.bwav": "这里是……？",
  "DmT_ZE_Meet_Text_012_b.bwav": "我好像吓到你了呢。",
  "DmT_ZE_Meet_Text_013_b.bwav": "",
  "DmT_ZE_Meet_Text_014_b.bwav": "对不起。",
  "DmT_ZE_Meet_Text_015_c.bwav": "我是索尼娅。",
  "DmT_ZE_Meet_Text_016_c.bwav": "",
  "DmT_ZE_Meet_Text_018_b.bwav": "你叫什么名字？",
  "DmT_ZE_Meet_Text_019_b.bwav": "我、我是……海拉鲁国王罗姆的女儿，塞尔达。",
  "DmT_ZE_Meet_Text_020_b.bwav": "",
  "DmT_ZE_Meet_Text_021_b.bwav": "这可真是奇怪，\n海拉鲁是我们兴建的国家，除了我以外还有其他国王吗？",
  "DmT_ZE_Meet_Text_021_bb.bwav": "",
  "DmT_ZE_Meet_Text_021_c.bwav": "",
  "DmT_ZE_Meet_Text_022_c.bwav": "由两位兴建的国家？\n……你就是国王？",
  "DmT_ZE_Meet_Text_023_b.bwav": "正是，我叫劳鲁，\n是这个国家的国王。",
  "DmT_ZE_Meet_Text_024_c.bwav": "劳鲁……国王和……\n索尼娅……王后？",
  "DmT_ZE_Meet_Text_025_c.bwav": "",
  "DmT_ZE_Meet_Text_027_b.bwav": "难道……？",
  "DmT_ZE_Molduga_Text_000_abb.bwav": "海拉鲁王国将落入我手……",
  "DmT_ZE_Molduga_Text_000_ac.bwav": "",
  "DmT_ZE_Molduga_Text_000_b.bwav": "一大群莫尔德拉吉克正在接近！",
  "DmT_ZE_Molduga_Text_001_b.bwav": "总数不明！\n总、总之数量极多！！",
  "DmT_ZE_Molduga_Text_002_bb.bwav": "居然会有那么多莫尔德拉吉克！\n究竟发生了什么……",
  "DmT_ZE_Molduga_Text_002_d.bwav": "",
  "DmT_ZE_Molduga_Text_003_b.bwav": "",
  "DmT_ZE_Molduga_Text_003_bc.bwav": "",
  "DmT_ZE_Molduga_Text_003_d.bwav": "",
  "DmT_ZE_Molduga_Text_004_aab.bwav": "",
  "DmT_ZE_Molduga_Text_004_ac.bwav": "",
  "DmT_ZE_Molduga_Text_004_b.bwav": "",
  "DmT_ZE_Molduga_Text_005_c.bwav": "",
  "DmT_ZE_Molduga_Text_006_ab.bwav": "",
  "DmT_ZE_Molduga_Text_006_b.bwav": "",
  "DmT_ZE_Molduga_Text_007_bab.bwav": "",
  "DmT_ZE_Molduga_Text_007_c.bwav": "莫尔德拉吉克居然在一瞬间就被解决了！",
  "DmT_ZE_Molduga_Text_007_cb.bwav": "刚才的究竟是……",
  "DmT_ZE_Molduga_Text_008_ab.bwav": "",
  "DmT_ZE_Molduga_Text_008_ac.bwav": "仅凭蛮力不行啊……",
  "DmT_ZE_Molduga_Text_015_b.bwav": "那就是左纳乌的秘石……",
  "DmT_ZE_Molduga_Text_016_b.bwav": "有意思～",
  "DmT_ZE_QueenDead_Text_000_b.bwav": "好了，塞尔达。\n这里不会有人来的。",
  "DmT_ZE_QueenDead_Text_001_b.bwav": "你到底有什么事要跟我说呢？",
  "DmT_ZE_QueenDead_Text_002_ac.bwav": "",
  "DmT_ZE_QueenDead_Text_002_c.bwav": "真是愚蠢。",
  "DmT_ZE_QueenDead_Text_004_d.bwav": "",
  "DmT_ZE_QueenDead_Text_005_c.bwav": "",
  "DmT_ZE_QueenDead_Text_006_b.bwav": "哎呀……\n被你这种欺骗他人的人这么说……",
  "DmT_ZE_QueenDead_Text_007_b.bwav": "还真是令人吃惊啊。",
  "DmT_ZE_QueenDead_Text_008_b.bwav": "加侬多夫的……",
  "DmT_ZE_QueenDead_Text_009_b.bwav": "提线木偶。",
  "DmT_ZE_QueenDead_Text_011_d.bwav": "你难道以为……\n我们什么都没有察觉到吗？",
  "DmT_ZE_QueenDead_Text_012_aaac.bwav": "",
  "DmT_ZE_QueenDead_Text_012_aab.bwav": "",
  "DmT_ZE_QueenDead_Text_012_ac.bwav": "",
  "DmT_ZE_QueenDead_Text_012_c.bwav": "",
  "DmT_ZE_QueenDead_Text_013_b.bwav": "",
  "DmT_ZE_QueenDead_Text_014_b.bwav": "",
  "DmT_ZE_QueenDead_Text_015_c.bwav": "",
  "DmT_ZE_QueenDead_Text_017_ab.bwav": "",
  "DmT_ZE_QueenDead_Text_017_c.bwav": "",
  "DmT_ZE_QueenDead_Text_018_bb.bwav": "",
  "DmT_ZE_QueenDead_Text_018_d.bwav": "",
  "DmT_ZE_QueenDead_Text_019_b.bwav": "",
  "DmT_ZE_QueenDead_Text_020_b.bwav": "索尼娅大人！！！",
  "DmT_ZE_QueenDead_Text_021_b.bwav": "索尼娅大人！",
  "DmT_ZE_QueenDead_Text_022_b.bwav": "索尼娅大人——！\n索尼娅大人——！！",
  "DmT_ZE_QueenDead_Text_022_c.bwav": "",
  "DmT_ZE_QueenDead_Text_023_c.bwav": "",
  "DmT_ZE_QueenDead_Text_025_b.bwav": "",
  "DmT_ZN_BossIn_Text_002_b.bwav": "\n那是我曾经制作的魔像。",
  "DmT_ZN_BossIn_Text_003_b.bwav": "那股瘴气……\n魔像恐怕已经被怪物占据了。",
  "DmT_ZN_BossIn_Text_004_b.bwav": "这个魔像已经成为了魔王的傀儡，\n不能放任它不管。",
  "DmT_ZN_BossIn_Text_005_b.bwav": "林克，请和我一起战斗。",
  "DmT_ZO_Awake_Text_003_c.bwav": "与林克并肩作战是我的命运？",
  "DmT_ZO_Awake_Text_004_b.bwav": "",
  "DmT_ZO_Awake_Text_005_b.bwav": "我来这里只是为了拯救领地……",
  "DmT_ZO_Awake_Text_006_c.bwav": "没想到会被托付拯救整个海拉鲁的使命！",
  "DmT_ZO_Awake_Text_007_c.bwav": "我一定会像先祖大人一样保护海拉鲁！",
  "DmT_ZO_Awake_Text_008_b.bwav": "我会继承这个秘石的卓！",
  "DmT_ZO_Awake_Text_011_bb.bwav": "我是水之贤者！\n看好了！这就是贤者之力！",
  "DmT_ZO_Awake_Text_012_b.bwav": "",
  "DmT_ZO_Awake_Text_013_b.bwav": "好了，林克……伸出手吧。",
  "DmT_ZO_Awake_Text_013_c.bwav": "",
  "DmT_ZO_Awake_Text_014_b.bwav": "我以水之贤者希多之名，\n发誓与你并肩作战。",
  "DmT_ZO_Awake_Text_015_b.bwav": "希望你能收下它！这就是证明卓！！",
  "DmT_ZO_Awake_Text_018_c.bwav": "有了这枚戒指，\n我的力量将会一直与林克你同在卓。",
  "DmT_ZO_Awake_Text_019_b.bwav": "以后也多多关照了，林克！\n好了，我们回领地去吧！",
  "DmT_ZO_BossIn_Text_001_b.bwav": "",
  "DmT_ZO_BossIn_Text_002_b.bwav": "",
  "DmT_ZO_BossIn_Text_003_c.bwav": "哦哦，淤泥不见了卓！\n这样一来，领地也……",
  "DmT_ZO_BossIn_Text_006_b.bwav": "",
  "DmT_ZO_BossIn_Text_007_b.bwav": "怎么了！？",
  "DmT_ZO_BossIn_Text_008_b.bwav": "果然是怪物！\n你就是袭击领地的罪魁祸首吧！！",
  "DmT_ZO_BossIn_Text_009_c.bwav": "可恶！",
  "DmT_ZO_BossIn_Text_011_b.bwav": "要上了卓，林克！！",
  "DmT_ZO_MeetAgain_Text_004_b.bwav": "",
  "DmT_ZO_MeetAgain_Text_005_b.bwav": "",
  "DmT_ZO_MeetAgain_Text_008_b.bwav": "真的是你吗……？",
  "DmT_ZO_MeetAgain_Text_008_c.bwav": "",
  "DmT_ZO_MeetAgain_Text_011_ab.bwav": "",
  "DmT_ZO_MeetAgain_Text_011_b.bwav": "我可想你了卓，林克！！",
  "DmT_ZO_StoneGet_Text_001_c.bwav": "",
  "DmT_ZO_StoneGet_Text_001_d.bwav": "",
  "DmT_ZO_StoneGet_Text_002_c.bwav": "",
  "DmT_ZO_StoneGet_Text_003_c.bwav": "",
  "DmT_ZO_StoneGet_Text_004_c.bwav": "",
  "DmT_ZO_StoneMind_Text_000_b.bwav": "后代啊……\n继承吾血之人，希多……",
  "DmT_ZO_StoneMind_Text_001_b.bwav": "这声音是……",
  "DmT_ZO_StoneMind_Text_002_b.bwav": "刚才一直向我们搭话的……？",
  "DmT_ZO_StoneMind_Text_003_c.bwav": "吾乃汝遥远之祖先。",
  "DmT_ZO_StoneMind_Text_004_b.bwav": "吾侍奉初代海拉鲁国王，身为卓拉族战士，\n亦是司水之贤者……",
  "DmT_ZO_StoneMind_Text_005_b.bwav": "汝战斗自如，行云流水，实乃出色。\n不愧为吾之后代……卓拉之骄傲。",
  "DmT_ZO_StoneMind_Text_006_b.bwav": "那即是淤泥之元凶，\n乃魔王所遣之怪物。",
  "DmT_ZO_StoneMind_Text_007_b.bwav": "其目的在于阻止汝得到\n先前所触之石——秘石。",
  "DmT_ZO_StoneMind_Text_008_b.bwav": "你说魔王和秘石？",
  "DmT_ZO_StoneMind_Text_009_b.bwav": "诚然……此二者于汝今后之途，至关重要。",
  "DmT_ZO_StoneMind_Text_010_c.bwav": "因此，愿汝仔细倾听……",
  "DmT_ZO_StoneMind_Text_012_b.bwav": "封印战争之悲剧……\n及吾等一族之命运……",
  "DmT_ZO_Vortex_Text_001_b.bwav": "",
  "DmT_ZO_Vortex_Text_001_c.bwav": "我有一个想法！",
  "DmT_ZO_Vortex_Text_002_b.bwav": "",
  "DmT_ZO_Vortex_Text_003_b.bwav": "",
  "DmT_ZO_Vortex_Text_004_b.bwav": "",
  "DmT_ZO_Vortex_Text_005_b.bwav": "果然和我想的一样！这底下有个类似入口的东西！",
  "DmT_ZO_Vortex_Text_006_b.bwav": "让我来为你开辟道路！你就跳进去吧，林克！",
  "Dm_BC_0012_Text_000_b.bwav": "塞尔达殿下和你去海拉鲁城堡\n进行了调查。",
  "Dm_BC_0012_Text_001_b.bwav": "然后，你们在地下深处发现了一具木乃伊。",
  "Dm_BC_0012_Text_002_b.bwav": "它在你们的面前苏醒了过来……",
  "Dm_BC_0012_Text_003_b.bwav": "塞尔达殿下在地底失去踪影。",
  "Dm_BC_0012_Text_004_b.bwav": "城堡浮了起来，许多遗迹从天上坠落，\n大混乱就是在那时候发生的吧。",
  "Dm_BC_0012_Text_005_c.bwav": "你最后流落到了浮岛上……\n木乃伊身上的右手保护了你。",
  "Dm_BC_0012_Text_006_b.bwav": "后来又有个奇怪的家伙\n把普尔亚平板交给了你……",
  "Dm_BC_0012_Text_007_c.bwav": "这只右手的主人是一个叫劳鲁的人……",
  "Dm_BC_0012_Text_008_c.bwav": "大师之剑也不见了……",
  "Dm_BC_0012_Text_010_b.bwav": "你听了塞尔达殿下的声音寻到这里……",
  "Dm_BZ_0002_Text_004_b.bwav": "",
  "Dm_BZ_0002_Text_005_b.bwav": "那、那是！？",
  "Dm_BZ_0002_Text_006_b.bwav": "",
  "Dm_BZ_0002_Text_007_b.bwav": "林克！快看这个！",
  "Dm_BZ_0002_Text_008_b.bwav": "快！！",
  "Dm_BZ_0002_Text_010_c.bwav": "公主殿下……",
  "Dm_BZ_0002_Text_011_b.bwav": "",
  "Dm_BZ_0002_Text_012_b.bwav": "",
  "Dm_BZ_0005_Text_000_ab.bwav": "",
  "Dm_BZ_0005_Text_000_b.bwav": "出来吧，我的仆人们。",
  "Dm_BZ_0005_Text_001_b.bwav": "为我赐予你们的力量骄傲吧，把支配这块土地的海拉鲁王国……",
  "Dm_BZ_0005_Text_002_b.bwav": "还有与他们伙同的人……",
  "Dm_BZ_0005_Text_003_b.bwav": "全都赶尽杀绝！！",
  "Dm_BZ_0006_Text_000_b.bwav": "林克……我在等你……",
  "Dm_BZ_0006_Text_001_b.bwav": "我一直在等着你……",
  "Dm_BZ_0007_Text_000_b.bwav": "……林克。",
  "Dm_BZ_0007_Text_001_b.bwav": "……林克。",
  "Dm_BZ_0007_Text_002_b.bwav": "快来我这里……",
  "Dm_BZ_0007_Text_003_b.bwav": "我在等你……",
  "Dm_BZ_0007_Text_004_b.bwav": "我在……等着你……",
  "Dm_ED_0004_Text_000_ab.bwav": "",
  "Dm_ED_0004_Text_000_b.bwav": "",
  "Dm_ED_0004_Text_000_c.bwav": "",
  "Dm_ED_0004_Text_001_b.bwav": "",
  "Dm_ED_0004_Text_001_c.bwav": "",
  "Dm_ED_0004_Text_002_b.bwav": "林克……\n为什么你……",
  "Dm_ED_0004_Text_002_c.bwav": "",
  "Dm_ED_0004_Text_003_b.bwav": "我……",
  "Dm_ED_0004_Text_004_b.bwav": "",
  "Dm_ED_0004_Text_005_ab.bwav": "",
  "Dm_ED_0004_Text_005_b.bwav": "你……收到了啊……",
  "Dm_ED_0004_Text_006_b.bwav": "",
  "Dm_ED_0004_Text_007_b.bwav": "魔王……\n已经被打倒了……",
  "Dm_ED_0004_Text_008_b.bwav": "我不是在做梦吧……",
  "Dm_ED_0004_Text_009_b.bwav": "太好了……",
  "Dm_ED_0004_Text_010_b.bwav": "真的太好了！",
  "Dm_ED_0004_Text_011_b.bwav": "但是，为什么我……",
  "Dm_ED_0004_Text_012_b.bwav": "不，\n我很清楚为什么……",
  "Dm_ED_0004_Text_013_b.bwav": "我……\n只是一直沉睡着而已。",
  "Dm_ED_0004_Text_014_b.bwav": "直到被非常巨大的……\n温暖的东西所包围，这才醒了过来。",
  "Dm_ED_0004_Text_015_b.bwav": "谢谢你。",
  "Dm_ED_0004_Text_019_b.bwav": "我在遥远的时代遇见了许多不同的人……",
  "Dm_ED_0004_Text_020_b.bwav": "我有很多话想和你说……",
  "Dm_ED_0004_Text_021_b.bwav": "我回来了……林克。",
  "Dm_ED_0007_Text_000_ab.bwav": "",
  "Dm_ED_0007_Text_003_c.bwav": "居然能让这么广阔的土地飘浮在空中……",
  "Dm_ED_0007_Text_003_d.bwav": "真是再次让人领悟到左纳乌文明的力量之强啊……",
  "Dm_ED_0007_Text_004_b.bwav": "很高兴能把你们带来这里……\n我一直想让你们从这里一睹海拉鲁的全貌。",
  "Dm_ED_0007_Text_005_b.bwav": "哇……\n我从来没来过这么高的地方鼓咯。",
  "Dm_ED_0007_Text_006_b.bwav": "是啊，这景色真是壮丽……",
  "Dm_ED_0007_Text_007_b.bwav": "……原来塞尔达一直都在这片空中啊……",
  "Dm_ED_0007_Text_008_b.bwav": "是的，\n虽然我已经记不得了……",
  "Dm_ED_0007_Text_009_b.bwav": "但没想到……\n我还能再一次站在这里……",
  "Dm_ED_0007_Text_014_b.bwav": "虽然这只是我的推论……",
  "Dm_ED_0007_Text_015_b.bwav": "但或许是因为劳鲁与索尼娅二人……",
  "Dm_ED_0007_Text_016_b.bwav": "将各自的光与时之力借给了林克，\n才引发了如此奇迹……",
  "Dm_ED_0007_Text_017_b.bwav": "",
  "Dm_ED_0007_Text_018_c.bwav": "是啊……",
  "Dm_ED_0007_Text_019_b.bwav": "……看来……时候到了。",
  "Dm_ED_0007_Text_020_b.bwav": "米涅鲁大人……",
  "Dm_ED_0007_Text_023_b.bwav": "我们在遥远过去不得不托付于未来解决的灾厄，\n如今由你们成功驱除……",
  "Dm_ED_0007_Text_024_b.bwav": "如此一来，我也可以安心追随劳鲁他们而去了。",
  "Dm_ED_0007_Text_024_c.bwav": "",
  "Dm_ED_0007_Text_024_cb.bwav": "",
  "Dm_ED_0007_Text_024_d.bwav": "",
  "Dm_ED_0007_Text_024_e.bwav": "",
  "Dm_ED_0007_Text_025_c.bwav": "",
  "Dm_ED_0007_Text_025_d.bwav": "",
  "Dm_ED_0007_Text_025_e.bwav": "",
  "Dm_ED_0007_Text_026_c.bwav": "",
  "Dm_ED_0007_Text_026_d.bwav": "",
  "Dm_ED_0007_Text_026_e.bwav": "",
  "Dm_ED_0007_Text_027_c.bwav": "",
  "Dm_ED_0007_Text_027_d.bwav": "",
  "Dm_ED_0007_Text_027_e.bwav": "",
  "Dm_ED_0007_Text_028_d.bwav": "",
  "Dm_ED_0007_Text_028_db.bwav": "我等……",
  "Dm_ED_0007_Text_028_e.bwav": "",
  "Dm_ED_0007_Text_028_eb.bwav": "齐聚在此……",
  "Dm_ED_0007_Text_028_f.bwav": "",
  "Dm_ED_0007_Text_028_g.bwav": "立下誓言……",
  "Dm_ED_0007_Text_029_b.bwav": "",
  "Dm_ED_0007_Text_030_b.bwav": "",
  "Dm_ED_0007_Text_031_b.bwav": "",
  "Dm_ED_0007_Text_032_b.bwav": "",
  "Dm_ED_0007_Text_032_bab.bwav": "今后亦将为塞尔达公主效力……",
  "Dm_ED_0007_Text_032_cb.bwav": "",
  "Dm_ED_0007_Text_032_db.bwav": "",
  "Dm_ED_0007_Text_032_eb.bwav": "",
  "Dm_ED_0007_Text_032_fb.bwav": "",
  "Dm_ED_0007_Text_032_fc.bwav": "",
  "Dm_ED_0007_Text_033_c.bwav": "",
  "Dm_ED_0007_Text_034_c.bwav": "",
  "Dm_ED_0007_Text_035_c.bwav": "",
  "Dm_ED_0007_Text_036_b.bwav": "",
  "Dm_ED_0007_Text_036_bb.bwav": "",
  "Dm_ED_0007_Text_036_c.bwav": "",
  "Dm_ED_0007_Text_037_b.bwav": "",
  "Dm_ED_0007_Text_038_b.bwav": "",
  "Dm_ED_0007_Text_039_b.bwav": "",
  "Dm_ED_0007_Text_040_b.bwav": "",
  "Dm_ED_0007_Text_040_bb.bwav": "我等立誓，为塞尔达公主效力，捍卫海拉鲁之安宁！",
  "Dm_ED_0007_Text_041_aab.bwav": "",
  "Dm_ED_0007_Text_041_ab.bwav": "",
  "Dm_ED_0007_Text_041_b.bwav": "我也会转达给劳鲁和索尼娅的……",
  "Dm_ED_0007_Text_042_b.bwav": "米涅鲁大人……",
  "Dm_ED_0007_Text_044_b.bwav": "",
  "Dm_ED_0007_Text_045_b.bwav": "……你的心意，他们也一定会知晓……",
  "Dm_ED_0007_Text_046_b.bwav": "",
  "Dm_ED_0007_Text_046_c.bwav": "",
  "Dm_ED_0007_Text_047_b.bwav": "谢谢你……",
  "Dm_ED_0007_Text_048_ab.bwav": "",
  "Dm_ED_0007_Text_056_cb.bwav": "",
  "Dm_ED_0007_Text_058_c.bwav": "劳鲁大人……索尼娅大人……米涅鲁大人……\n还有各位古代贤者……",
  "Dm_ED_0007_Text_059_c.bwav": "他们期望的并非一时的平安，\n而是海拉鲁长久的安宁……",
  "Dm_ED_0007_Text_060_c.bwav": "我想要回应这一期望。",
  "Dm_ED_0007_Text_061_c.bwav": "从今往后，我都会投身于此……",
  "Dm_ED_0007_Text_062_c.bwav": "……各位，\n请你们……",
  "Dm_ED_0007_Text_064_b.bwav": "助我一臂之力吧！",
  "Dm_GA_0001_Text_000_b.bwav": "你一个人独闯也太见外了吧！",
  "Dm_GA_0001_Text_001_b.bwav": "你一个人独闯也太见外了鼓咯。",
  "Dm_GA_0001_Text_002_b.bwav": "你一个人独闯也太见外了卓。",
  "Dm_GA_0001_Text_003_b.bwav": "你一个人独闯也太见外了。",
  "Dm_GA_0001_Text_005_b.bwav": "林克，你并非孤身一人。",
  "Dm_GA_0008_Text_001_b.bwav": "",
  "Dm_GA_0008_Text_002_b.bwav": "",
  "Dm_GA_0008_Text_003_b.bwav": "",
  "Dm_GA_0009_Text_000_ab.bwav": "这家伙！\n是打算夹击我们啊！",
  "Dm_GA_0009_Text_001_b.bwav": "林克！这家伙就交给我吧！\n我想试一下我的力量！",
  "Dm_GA_0010_Text_000_aab.bwav": "这家伙！\n是打算夹击我们鼓咯！",
  "Dm_GA_0010_Text_000_ab.bwav": "",
  "Dm_GA_0010_Text_000_b.bwav": "林克！就让我来当它的对手吧鼓咯！\n让你见识一下贤者之力鼓咯！！",
  "Dm_GA_0011_Text_000_ab.bwav": "这家伙……又出现了啊！",
  "Dm_GA_0011_Text_000_c.bwav": "打算切断我们的后路吗？\n我可不会让你得逞！",
  "Dm_GA_0011_Text_001_b.bwav": "林克！这家伙就让我来打倒吧卓！",
  "Dm_GA_0012_Text_000_aab.bwav": "原来是要夹击我们吗……！",
  "Dm_GA_0012_Text_000_ab.bwav": "",
  "Dm_GA_0012_Text_000_b.bwav": "对付这家伙我一个人就足够了，\n它的弱点我早已看透！",
  "Dm_GA_0012_Text_001_b.bwav": "林克！\n你先走吧，去达成我们的目的！",
  "Dm_GA_0013_Text_000_ab.bwav": "那是……！\n用魔力仿造了我的魔像吗……",
  "Dm_GA_0013_Text_001_b.bwav": "看来是打算断绝我们的退路啊……\n但是，区区赝品不足畏惧！",
  "Dm_GA_0015_Text_000_b.bwav": "真是可悲……",
  "Dm_GA_0015_Text_001_b.bwav": "本应被黑暗笼罩的这个世界，\n现在竟充满了可恨的光芒。",
  "Dm_GA_0015_Text_002_b.bwav": "贪图安逸的废物们成群跋扈……",
  "Dm_GA_0015_Text_003_b.bwav": "还是从前更能让我感受到气魄……",
  "Dm_GA_0015_Text_004_b.bwav": "从今往后，\n这片土地将恢复它应有的样貌。",
  "Dm_GA_0015_Text_005_b.bwav": "世界将由我统治，\n由我裁定。",
  "Dm_GA_0015_Text_006_b.bwav": "……这才是为王者应行之事。",
  "Dm_GA_0015_Text_007_b.bwav": "倾耳拭目吧……",
  "Dm_GA_0015_Text_008_b.bwav": "见证真正王者的复活……",
  "Dm_GA_0015_Text_009_b.bwav": "以及其世界的开端！",
  "Dm_GA_0016_Text_000_c.bwav": "",
  "Dm_GA_0016_Text_001_c.bwav": "",
  "Dm_GA_0016_Text_002_c.bwav": "",
  "Dm_GA_0016_Text_003_c.bwav": "",
  "Dm_GA_0016_Text_004_c.bwav": "",
  "Dm_GA_0016_Text_005_c.bwav": "",
  "Dm_GA_0016_Text_006_b.bwav": "我乃……统领万物的……",
  "Dm_GA_0016_Text_007_c.bwav": "全能之王！！",
  "Dm_GA_0016_Text_008_b.bwav": "决不接受……！",
  "Dm_GA_0016_Text_009_b.bwav": "决不接受自己被区区一介人类……！！",
  "Dm_GA_0016_Text_010_b.bwav": "",
  "Dm_GA_0016_Text_011_b.bwav": "",
  "Dm_GA_0016_Text_012_b.bwav": "",
  "Dm_GA_0016_Text_012_c.bwav": "",
  "Dm_GA_0016_Text_013_ab.bwav": "",
  "Dm_GA_0016_Text_013_b.bwav": "自我和肉体都已毫无意义！",
  "Dm_GA_0016_Text_014_b.bwav": "我要你们陪我一起堕入地狱！！",
  "Dm_GA_0016_Text_015_b.bwav": "让这个世界在无尽的黑暗中迎来终焉！！",
  "Dm_GA_0016_Text_016_b.bwav": "",
  "Dm_GA_0016_Text_017_b.bwav": "",
  "Dm_GA_0016_Text_018_b.bwav": "",
  "Dm_GA_0016_Text_019_ac.bwav": "",
  "Dm_GA_0016_Text_020_b.bwav": "林克！",
  "Dm_GA_0016_Text_021_b.bwav": "林克！",
  "Dm_GA_0016_Text_022_b.bwav": "林克！",
  "Dm_GA_0016_Text_023_b.bwav": "林克！",
  "Dm_GA_0016_Text_024_b.bwav": "林克！",
  "Dm_GA_0017_Text_005_bb.bwav": "",
  "Dm_GA_0017_Text_005_bc.bwav": "",
  "Dm_GA_0017_Text_005_bd.bwav": "",
  "Dm_GA_0017_Text_005_be.bwav": "",
  "Dm_GA_0017_Text_005_bf.bwav": "",
  "Dm_GA_0017_Text_005_d.bwav": "那是……魔王的瘴气吗！\n那家伙就在那里！？",
  "Dm_GA_0017_Text_005_e.bwav": "",
  "Dm_GA_0017_Text_006_d.bwav": "可恶的魔王！居然又创造出这些家伙来……\n打算夹击我们吗！！",
  "Dm_GA_0017_Text_006_e.bwav": "",
  "Dm_GA_0017_Text_007_b.bwav": "",
  "Dm_GA_0017_Text_008_b.bwav": "",
  "Dm_GA_0017_Text_009_b.bwav": "",
  "Dm_GA_0017_Text_010_b.bwav": "",
  "Dm_GA_0017_Text_011_b.bwav": "",
  "Dm_GA_0017_Text_012_d.bwav": "这些家伙是我们命中注定的对手！",
  "Dm_GA_0017_Text_013_c.bwav": "林克，不用你插手卓！！",
  "Dm_GA_0017_Text_014_c.bwav": "林克，你就继续前进吧鼓咯！",
  "Dm_GA_0017_Text_015_c.bwav": "让你见识见识贤者之力鼓咯！",
  "Dm_GA_0017_Text_016_c.bwav": "放心吧！对手可是手下败将！",
  "Dm_GA_0017_Text_017_d.bwav": "交给我们绰绰有余！",
  "Dm_GA_0017_Text_018_c.bwav": "请快走吧，林克。",
  "Dm_GA_0017_Text_022_b.bwav": "一切都交给你了。",
  "Dm_GA_0018_Text_000_aaaaab.bwav": "你一个人独闯也太见外了吧！",
  "Dm_GA_0018_Text_000_c.bwav": "林克你可不是一个人在战斗啊！",
  "Dm_GA_0018_Text_000_d.bwav": "你还有我在！",
  "Dm_GA_0018_Text_001_c.bwav": "我也继承了先祖大人的意志，",
  "Dm_GA_0018_Text_001_d.bwav": "要和你一起战斗鼓咯！",
  "Dm_GA_0018_Text_002_d.bwav": "林克，",
  "Dm_GA_0018_Text_002_e.bwav": "我们也要一起守护海拉鲁！",
  "Dm_GA_0018_Text_003_c.bwav": "格鲁德族受了你不少恩……",
  "Dm_GA_0018_Text_003_d.bwav": "现在正是报答你的时候！",
  "Dm_GA_0018_Text_004_d.bwav": "远古时期犯下的过失就趁现在弥补。",
  "Dm_GA_0018_Text_004_e.bwav": "就此了断与魔王之间长久的因缘！",
  "Dm_GA_0018_Text_005_c.bwav": "",
  "Dm_GA_0018_Text_006_c.bwav": "",
  "Dm_GA_0018_Text_007_c.bwav": "",
  "Dm_GA_0018_Text_008_c.bwav": "",
  "Dm_GA_0018_Text_009_c.bwav": "",
  "Dm_GA_0019_Text_000_b.bwav": "",
  "Dm_GA_0019_Text_001_b.bwav": "",
  "Dm_GA_0019_Text_002_b.bwav": "",
  "Dm_GA_0019_Text_003_b.bwav": "",
  "Dm_GA_0019_Text_004_b.bwav": "",
  "Dm_GA_0019_Text_031_b.bwav": "……魔王的瘴气？\n那家伙就在那里吗……！？",
  "Dm_GA_0019_Text_032_b.bwav": "那是，魔王的瘴气吗鼓咯？\n那家伙就在那里吗……！？",
  "Dm_GA_0019_Text_033_b.bwav": "那是魔王的瘴气吗？\n那家伙就在那里……！？",
  "Dm_GA_0019_Text_034_b.bwav": "……魔王的瘴气？\n那家伙就在那里吗……！？",
  "Dm_GA_0019_Text_035_b.bwav": "那是魔王的瘴气！\n那家伙就在那里。",
  "Dm_GE_0009_Text_009_b.bwav": "……请……",
  "Dm_GE_0009_Text_010_b.bwav": "……来……",
  "Dm_GE_0009_Text_011_b.bwav": "请来寻吾……",
  "Dm_GE_0018_Text_002_b.bwav": "后代啊……吾之后代啊……",
  "Dm_GE_0018_Text_003_b.bwav": "此机关\n连接着神殿的顶端。",
  "Dm_GE_0018_Text_004_b.bwav": "若使用汝之力量使4个蓄电池充满雷之力，\n机关便能觉醒。",
  "Dm_GE_0018_Text_005_b.bwav": "遵从吾之引导即可……",
  "Dm_GE_0025_Text_000_b.bwav": "事发之时距今已远。\n彼时海拉鲁王国于此地初建……",
  "Dm_GE_0025_Text_001_b.bwav": "一穷凶极恶者现身于世，袭击无罪之人，欲使家国倾覆。\n此人即是魔王……",
  "Dm_GE_0025_Text_002_b.bwav": "此男子曾为吾等格鲁德族之首领，\n却因其对力量的虚妄执念堕为怪物……",
  "Dm_GE_0025_Text_003_b.bwav": "而初代海拉鲁国王劳鲁与六名战士挺身而出，\n决心与其对抗。",
  "Dm_GE_0025_Text_004_b.bwav": "劳鲁交予吾等一物，\n以助吾等与魔王交战。",
  "Dm_GE_0025_Text_005_b.bwav": "此物即秘石……\n是为倍增持有者力量之秘宝。",
  "Dm_GE_0025_Text_005_c.bwav": "劳鲁交予吾等秘石，\n以助吾等与魔王交战。",
  "Dm_GE_0025_Text_005_d.bwav": "此物乃倍增持有者力量之秘宝。",
  "Dm_GE_0025_Text_006_b.bwav": "吾为六战士之一，乃雷之贤者，\n亦携秘石与其交锋。",
  "Dm_GE_0025_Text_007_b.bwav": "然，魔王强悍之甚……",
  "Dm_GE_0025_Text_008_b.bwav": "面对吾之雷击，其顽强不动丝毫，\n霸气亦不让半分……",
  "Dm_GE_0025_Text_010_c.bwav": "国王劳鲁遂醒悟，\n吾等并无击败魔王之力。",
  "Dm_GE_0025_Text_011_b.bwav": "彼如此抉择——\n以一己之身封印魔王，换战争终结。",
  "Dm_GE_0025_Text_012_b.bwav": "此乃“封印战争”……",
  "Dm_GE_0025_Text_014_c.bwav": "吾等得以幸存，而后不久……\n一人寻至吾所，决定了吾等格鲁德族之宿命。",
  "Dm_GE_0025_Text_015_c.bwav": "此人即六贤者之一——时之贤者。",
  "Dm_GE_0025_Text_015_d.bwav": "而后不久……",
  "Dm_GE_0025_Text_015_e.bwav": "六贤者之一——时之贤者寻至吾所，\n决定了吾等格鲁德族之宿命。",
  "Dm_GE_0025_Text_017_c.bwav": "魔王的封印总有一天会被解除，然后复活于世。",
  "Dm_GE_0025_Text_018_c.bwav": "到那时，他……\n剑士林克必须拥有与之抗衡的力量。",
  "Dm_GE_0025_Text_019_c.bwav": "请务必将你们的力量借与他……\n司掌雷的格鲁德族的力量！",
  "Dm_GE_0025_Text_020_b.bwav": "此乃吾等使命确立之刹那……",
  "Dm_GE_0025_Text_021_c.bwav": "讨伐魔王乃吾等大愿。",
  "Dm_GE_0025_Text_022_b.bwav": "魔王诞生，格鲁德一族难辞其咎……\n吾等必须为此赎罪。",
  "Dm_GE_0025_Text_023_b.bwav": "待魔王复活之时，\n吾等格鲁德一族将再次觉醒为雷之贤者，",
  "Dm_GE_0025_Text_024_b.bwav": "誓与剑士林克一同战斗。",
  "Dm_GE_0026_Text_000_c.bwav": "此乃封印战争始末，\n及吾等一族宿命！",
  "Dm_GE_0026_Text_001_b.bwav": "……汝等竭力拼搏，救格鲁德小镇于水火。\n然魔王复活之日将近。",
  "Dm_GE_0026_Text_002_b.bwav": "吾之后代，露珠。",
  "Dm_GE_0026_Text_003_b.bwav": "请继承此秘石，\n履行吾与时之贤者所定之约……",
  "Dm_GE_0026_Text_004_b.bwav": "发誓与剑士林克\n一同作战。",
  "Dm_GE_0029_Text_000_b.bwav": "林克！\n这次我们一定要做个了断！",
  "riju_death_02.bwav": "林克……\\0抱歉……",
  "riju_death_03.bwav": "",
  "Dm_GO_0013_Text_003_b.bwav": "……请……",
  "Dm_GO_0013_Text_004_b.bwav": "……来……",
  "Dm_GO_0013_Text_005_b.bwav": "请来寻吾……",
  "Dm_GO_0015_Text_001_b.bwav": "后代啊……吾之后代啊……",
  "Dm_GO_0015_Text_002_b.bwav": "汝欲开启的那扇门\n被5把挂锁牢牢封闭。",
  "Dm_GO_0015_Text_003_b.bwav": "使用汝所拥有的力量解开所有的锁，\n那扇门便会打开。",
  "Dm_GO_0015_Text_003_c.bwav": "遵从吾之指引吧……",
  "Dm_GO_0018_00.bwav": "馚㺙林克！这就是挂锁吧！\n剩下4处……还有很多鼓咯。",
  "Dm_GO_0018_01.bwav": "馚㺙还剩下3处鼓咯！\n林克！抓紧时间鼓咯！！",
  "Dm_GO_0018_02.bwav": "馚㺙林克！还剩下2处鼓咯！\n保持这个势头鼓咯！",
  "Dm_GO_0018_03.bwav": "馚㺙就差一口气了鼓咯！\n还剩下1处鼓咯！",
  "Dm_GO_0018_04.bwav": "馚㺙林克！\n所有的锁都解开了鼓咯。\n馚㺙现在应该就能打开那扇门了……\n好，我们走吧鼓咯！",
  "Dm_GO_0021_Text_016_b.bwav": "事发之时距今已远。\n彼时海拉鲁王国于此地初建……",
  "Dm_GO_0021_Text_017_b.bwav": "一穷凶极恶者现身于世，袭击无罪之人，欲使家国倾覆。\n此人即是魔王……",
  "Dm_GO_0021_Text_018_b.bwav": "而初代海拉鲁国王劳鲁与六名战士挺身而出，\n决心与其对抗。",
  "Dm_GO_0021_Text_019_b.bwav": "劳鲁交予吾等一物，\n以助吾等与魔王交战。",
  "Dm_GO_0021_Text_020_b.bwav": "此物即秘石……\n是为倍增持有者力量之秘宝。",
  "Dm_GO_0021_Text_020_c.bwav": "劳鲁交予吾等秘石，\n以助吾等与魔王交战。",
  "Dm_GO_0021_Text_020_d.bwav": "此物乃倍增持有者力量之秘宝。",
  "Dm_GO_0021_Text_021_b.bwav": "吾为六战士之一，乃火之贤者，\n亦携秘石与其交锋。",
  "Dm_GO_0021_Text_022_b.bwav": "然，魔王强悍之甚……",
  "Dm_GO_0021_Text_023_b.bwav": "其体魄之结实，力量之强大……\n可轻易弹开吾全力一击……",
  "Dm_GO_0021_Text_025_c.bwav": "国王劳鲁遂醒悟，\n吾等并无击败魔王之力。",
  "Dm_GO_0021_Text_026_b.bwav": "彼如此抉择——\n以一己之身封印魔王，换战争终结。",
  "Dm_GO_0021_Text_027_b.bwav": "此乃“封印战争”……",
  "Dm_GO_0021_Text_029_c.bwav": "吾等得以幸存，而后不久……\n一人寻至吾所，决定了吾等鼓隆族之天命。",
  "Dm_GO_0021_Text_030_c.bwav": "此人即六贤者之一——时之贤者。",
  "Dm_GO_0021_Text_030_d.bwav": "而后不久……",
  "Dm_GO_0021_Text_030_e.bwav": "六贤者之一——时之贤者寻至吾所，\n决定了吾等鼓隆族之天命。",
  "Dm_GO_0021_Text_032_c.bwav": "魔王的封印总有一天会被解除，然后复活于世。",
  "Dm_GO_0021_Text_033_c.bwav": "所以，他必须拥有\n与之抗衡的力量。",
  "Dm_GO_0021_Text_034_c.bwav": "司掌火的鼓隆族的力量……\n请务必将这份力量借与剑士林克。",
  "Dm_GO_0021_Text_035_b.bwav": "此乃吾等使命确立之刹那……",
  "Dm_GO_0021_Text_036_c.bwav": "讨伐魔王乃吾等本愿。",
  "Dm_GO_0021_Text_037_b.bwav": "待魔王复活之时，\n吾等鼓隆一族将再次觉醒为火之贤者，",
  "Dm_GO_0021_Text_038_b.bwav": "誓与剑士林克一同战斗。",
  "Dm_GO_0022_Text_000_c.bwav": "此乃封印战争全貌，\n及吾等一族之天命！",
  "Dm_GO_0022_Text_001_b.bwav": "……汝等竭力拼搏，救鼓隆城于水火。\n然魔王复活之日将近。",
  "Dm_GO_0022_Text_002_b.bwav": "吾之后代，阿沅啊。",
  "Dm_GO_0022_Text_003_b.bwav": "请继承此秘石，\n履行吾与时之贤者所定之约……",
  "Dm_GO_0022_Text_004_b.bwav": "发誓与剑士林克\n一同作战。",
  "Dm_GO_0023_Text_000_ab.bwav": "",
  "Dm_GO_0023_Text_000_b.bwav": "是塞尔达殿下鼓咯！",
  "Dm_GO_0023_Text_002_b.bwav": "",
  "Dm_OP_0004_Text_003_b.bwav": "林克阁下，你醒了啊。",
  "Dm_OP_0004_Text_004_b.bwav": "我从塞尔达阁下那里听说过你……",
  "Dm_OP_0004_Text_005_b.bwav": "你现在身负重伤，\n但万幸没有生命危险……",
  "Dm_OP_0004_Text_006_b.bwav": "当时你的手已经腐朽，危及生命，\n我只能出此下策……",
  "Dm_OP_0016_Text_001_b.bwav": "",
  "Dm_OP_0016_Text_002_b.bwav": "",
  "Dm_OP_0016_Text_003_b.bwav": "",
  "Dm_OP_0016_Text_004_b.bwav": "",
  "Dm_OP_0016_Text_005_b.bwav": "",
  "Dm_OP_0016_Text_006_b.bwav": "",
  "Dm_OP_0016_Text_009_b.bwav": "林克……",
  "Dm_OP_0016_Text_012_b.bwav": "林克……\n来寻找我吧……",
  "Dm_OP_0017_Text_000_b.bwav": "报告称，很多人接触这瘴气后，身体都出现了不适……",
  "Dm_OP_0017_Text_001_b.bwav": "不过这点瘴气，对你我二人并没有什么影响……",
  "Dm_OP_0017_Text_002_b.bwav": "可是，为什么海拉鲁城堡的地下会冒出这种东西……",
  "Dm_OP_0017_Text_003_b.bwav": "再往前调查下去可能难免有危险，\n但是有林克你在，我很放心。",
  "Dm_OP_0017_Text_004_b.bwav": "我们尽快查明原因吧。",
  "Dm_OP_0020_Text_000_aab.bwav": "林克，你还好吗？",
  "Dm_OP_0020_Text_000_ab.bwav": "",
  "Dm_OP_0020_Text_000_b.bwav": "这幅壁画……",
  "Dm_OP_0020_Text_000_c.bwav": "",
  "Dm_OP_0020_Text_000_d.bwav": "",
  "Dm_OP_0020_Text_001_b.bwav": "……在王族传承的古代文献中，",
  "Dm_OP_0020_Text_002_b.bwav": "记载着在远古神话时代，\n有一场人与魔王争夺世界霸权的战争。",
  "Dm_OP_0020_Text_003_b.bwav": "这幅壁画描绘的，也许就是那段传说……",
  "Dm_OP_0020_Text_003_c.bwav": "",
  "Dm_OP_0020_Text_003_d.bwav": "",
  "Dm_OP_0020_Text_004_b.bwav": "刚才的石像原型是左纳乌族……",
  "Dm_OP_0020_Text_004_c.bwav": "而这里的像是我们海利亚人……",
  "Dm_OP_0020_Text_004_d.bwav": "左纳乌族仿佛从天而降一般。",
  "Dm_OP_0020_Text_005_b.bwav": "",
  "Dm_OP_0020_Text_005_c.bwav": "我的祖先，海拉鲁王族的先人……",
  "Dm_OP_0020_Text_005_d.bwav": "据说是与从天上降临的\n神之一族结姻而生。",
  "Dm_OP_0020_Text_006_b.bwav": "如果这幅壁画上的内容属实，\n那么从天上降临的一族就是左纳乌族……",
  "Dm_OP_0020_Text_007_b.bwav": "左纳乌一族与大地上的海利亚人往来，并建立了国家……",
  "Dm_OP_0020_Text_007_c.bwav": "也就是海拉鲁王国……",
  "Dm_OP_0020_Text_008_b.bwav": "……然而后来邪恶之人出现，\n夺走了王国的强大力量……",
  "Dm_OP_0020_Text_009_b.bwav": "这些都和古代文献上的内容吻合……",
  "Dm_OP_0020_Text_009_c.bwav": "",
  "Dm_OP_0020_Text_010_b.bwav": "然后，魔王诞生了……",
  "Dm_OP_0020_Text_010_c.bwav": "人们为打倒魔王，发起了战争……",
  "Dm_OP_0020_Text_010_d.bwav": "",
  "Dm_OP_0020_Text_011_b.bwav": "……如果这里描绘的人物\n就是所谓的魔王……",
  "Dm_OP_0020_Text_012_b.bwav": "",
  "Dm_OP_0020_Text_012_c.bwav": "太惊人了……",
  "Dm_OP_0020_Text_012_d.bwav": "这壁画无疑描绘了古代文献上记载的大战——",
  "Dm_OP_0020_Text_013_b.bwav": "封印战争的全貌！",
  "Dm_OP_0020_Text_014_b.bwav": "林克！\n这可是重要发现！",
  "Dm_OP_0020_Text_014_c.bwav": "",
  "Dm_OP_0020_Text_015_b.bwav": "这是普尔亚为我制作的道具，\n还好我带过来了。",
  "Dm_OP_0020_Text_016_b.bwav": "它非常适合用来记录这种东西。",
  "Dm_OP_0020_Text_017_b.bwav": "",
  "Dm_OP_0020_Text_017_c.bwav": "后面的部分被埋起来了，没办法看呢……",
  "Dm_OP_0020_Text_017_d.bwav": "",
  "Dm_OP_0020_Text_017_e.bwav": "",
  "Dm_OP_0020_Text_018_b.bwav": "这里究竟是什么地方……",
  "Dm_OP_0020_Text_019_b.bwav": "答案一定就在前方。\n我们继续前进吧，林克。",
  "Dm_OP_0028_Text_000_ab.bwav": "很好，\n看来你已经成功把门打开了。",
  "Dm_OP_0028_Text_000_ac.bwav": "虽然你的身体被瘴气侵蚀，\n状况还不算完好……",
  "Dm_OP_0028_Text_000_ad.bwav": "但是你在神庙获得的祝福之光的力量，\n似乎也略微地净化了一些你体内的瘴气。",
  "Dm_OP_0028_Text_000_c.bwav": "虽然我和你相处的时间很短，\n但是能和你说上话，我很开心。",
  "Dm_OP_0028_Text_001_ab.bwav": "一切都正如塞尔达所言……",
  "Dm_OP_0028_Text_002_c.bwav": "那姑娘……",
  "Dm_OP_0028_Text_003_b.bwav": "就拜托你了……",
  "Dm_OP_0030_Text_000_b.bwav": "瘴气越来越浓了……",
  "Dm_OP_0030_Text_001_b.bwav": "往地下延伸的洞窟比我预料中深得多……\n我们谨慎地前进吧……",
  "Dm_OP_0035_Text_000_b.bwav": "只有拥有力量的人才能打开这扇门……",
  "Dm_OP_0035_Text_001_c.bwav": "抱歉，我似乎惊吓到你了。",
  "Dm_OP_0035_Text_002_c.bwav": "我是之前和你说话的人，\n也是你那右臂原来的主人。",
  "Dm_OP_0035_Text_002_d.bwav": "我叫劳鲁。",
  "Dm_OP_0035_Text_003_c.bwav": "出于某些原因，我早已没有了实体，\n抱歉以这个姿态与你相见。",
  "Dm_OP_0035_Text_004_c.bwav": "那么，这扇门理应能够靠我的右手打开，\n但看来它现在失去了力量。",
  "Dm_OP_0035_Text_004_d.bwav": "神圣之光满溢的空间，\n或许能恢复这只手的力量……",
  "Dm_OP_0035_Text_005_c.bwav": "对了……\n去这座岛上的神庙走一圈如何？",
  "Dm_OP_0035_Text_007_b.bwav": "想必能让它恢复力量。",
  "Dm_OT_0015_Text_000_b.bwav": "欢迎你们的到来。",
  "Dm_OT_0015_Text_001_b.bwav": "海拉鲁的公主祭司……",
  "Dm_OT_0015_Text_002_b.bwav": "还有大师之剑的主人，林克……",
  "Dm_OT_0015_Text_003_b.bwav": "你的剑……已经完全恢复了。",
  "Dm_OT_0015_Text_004_b.bwav": "它是时候再次回到你的手里了……",
  "Dm_OT_0015_Text_005_b.bwav": "非常感谢，德库树长老。",
  "Dm_OT_0015_Text_006_b.bwav": "你无需道谢，\n其实我什么都没有做……",
  "Dm_OT_0015_Text_007_b.bwav": "这把剑即使受损，也会自己恢复……\n只要时间足够，不论损伤多么严重都会复原……",
  "Dm_OT_0015_Text_008_b.bwav": "不仅如此……",
  "Dm_OT_0015_Text_009_b.bwav": "沐浴在神圣之力下，会让这把剑愈发强大……\n神圣之力越强，剑的力量越强……",
  "Dm_OT_0015_Text_010_b.bwav": "不愧是由女神打造的传说中的剑……",
  "Dm_OT_0015_Text_011_b.bwav": "能够变得更强的剑……",
  "Dm_OT_0015_Text_012_b.bwav": "大师之剑……",
  "Dm_RT_0010_Text_007_b.bwav": "……请……",
  "Dm_RT_0010_Text_008_b.bwav": "……来……",
  "Dm_RT_0010_Text_009_b.bwav": "请来寻吾……",
  "Dm_RT_0014_Text_019_b.bwav": "后代啊……吾之后代啊……",
  "Dm_RT_0014_Text_020_b.bwav": "汝眼前甲板上的门\n一共被上了5把锁……",
  "Dm_RT_0014_Text_021_b.bwav": "使用汝之力量将所有锁解开，\n那扇门便能开启。",
  "Dm_RT_0014_Text_023_b.bwav": "遵从吾之引导吧……",
  "Dm_RT_0015_00.bwav": "林克，这就是锁吧！\n还剩4处，继续找下去吧！",
  "Dm_RT_0015_01.bwav": "还剩3处！\n再加把劲，林克！",
  "Dm_RT_0015_02.bwav": "林克！只剩下2处了，\n马上就能看到终点了！",
  "Dm_RT_0015_03.bwav": "只剩下最后1处了，林克！\n胜利就在眼前！",
  "Dm_RT_0015_04.bwav": "林克！\n锁已经全部解开了！\n这样甲板上的门应该就能打开了。\n好了，我们走吧！",
  "Dm_RT_0018_Text_004_b.bwav": "",
  "Dm_RT_0018_Text_005_b.bwav": "",
  "Dm_RT_0018_Text_007_b.bwav": "",
  "Dm_RT_0018_Text_009_c.bwav": "",
  "Dm_RT_0018_Text_011_b.bwav": "",
  "Dm_RT_0022_Text_000_b.bwav": "事发之时距今已远。\n彼时海拉鲁王国于此地初建……",
  "Dm_RT_0022_Text_001_b.bwav": "一穷凶极恶者现身于世，袭击无罪之人，欲使家国倾覆。\n此人即是魔王……",
  "Dm_RT_0022_Text_002_b.bwav": "而初代海拉鲁国王劳鲁与六名战士挺身而出，\n决心与其对抗。",
  "Dm_RT_0022_Text_003_b.bwav": "劳鲁交予吾等一物，\n以助吾等与魔王交战。",
  "Dm_RT_0022_Text_004_b.bwav": "此物即秘石……\n是为倍增持有者力量之秘宝。",
  "Dm_RT_0022_Text_004_c.bwav": "劳鲁交予吾等秘石，\n以助吾等与魔王交战。",
  "Dm_RT_0022_Text_004_d.bwav": "此物乃倍增持有者力量之秘宝。",
  "Dm_RT_0022_Text_005_b.bwav": "吾为六战士之一，乃风之贤者，\n亦携秘石与其交锋。",
  "Dm_RT_0022_Text_006_b.bwav": "然，魔王强悍之甚……",
  "Dm_RT_0022_Text_007_b.bwav": "其速度之惊人，凭吾双翼也亦难寻其破绽，\n所拥有之魔力更是无穷尽……",
  "Dm_RT_0022_Text_009_c.bwav": "国王劳鲁遂醒悟，\n吾等并无击败魔王之力。",
  "Dm_RT_0022_Text_010_b.bwav": "彼如此抉择——\n以一己之身封印魔王，换战争终结。",
  "Dm_RT_0022_Text_011_b.bwav": "此乃“封印战争”……",
  "Dm_RT_0022_Text_013_c.bwav": "吾等得以幸存，而后不久……\n一人寻至吾所，决定了吾等利特族之使命。",
  "Dm_RT_0022_Text_014_c.bwav": "此人即六贤者之一——时之贤者。",
  "Dm_RT_0022_Text_014_d.bwav": "而后不久……",
  "Dm_RT_0022_Text_014_e.bwav": "六贤者之一——时之贤者寻至吾所，\n决定了吾等利特族之使命。",
  "Dm_RT_0022_Text_016_b.bwav": "魔王的封印总有一天会被解除，然后复活于世。",
  "Dm_RT_0022_Text_017_c.bwav": "到那时，\n剑士林克必须拥有与之抗衡的力量。",
  "Dm_RT_0022_Text_018_c.bwav": "请务必将你们的力量……\n将司掌风的利特族的力量借与他。",
  "Dm_RT_0022_Text_019_b.bwav": "此乃吾等使命确立之刹那……",
  "Dm_RT_0022_Text_020_b.bwav": "讨伐魔王乃吾等夙愿。",
  "Dm_RT_0022_Text_021_b.bwav": "待魔王复活之时，\n吾等利特一族将再次觉醒为风之贤者，",
  "Dm_RT_0022_Text_022_b.bwav": "誓与剑士林克一同战斗。",
  "Dm_RT_0023_Text_000_c.bwav": "此乃封印战争经过，\n及吾等一族使命！",
  "Dm_RT_0023_Text_001_b.bwav": "……汝等竭力拼搏，救利特村于水火。\n然魔王复活之日将近。",
  "Dm_RT_0023_Text_002_b.bwav": "吾之后代，丘栗啊。",
  "Dm_RT_0023_Text_003_b.bwav": "请继承此秘石，\n履行吾与时之贤者所定之约……",
  "Dm_RT_0023_Text_004_b.bwav": "发誓与剑士林克\n一同作战。",
  "Dm_RT_0039_Text_000_b.bwav": "我没有逞强！\n我已经是一名战士了！",
  "Dm_RT_0039_Text_001_b.bwav": "只是去调查那朵巨大的云而已，\n我一个人就能轻松搞定的！",
  "Dm_RT_0039_Text_001_c.bwav": "",
  "Dm_RT_0039_Text_002_b.bwav": "再这样拖下去，",
  "Dm_RT_0039_Text_002_c.bwav": "村子就……",
  "Dm_RT_0039_Text_002_d.bwav": "",
  "Dm_RT_0039_Text_003_b.bwav": "莫非是……？",
  "Dm_RT_0039_Text_003_c.bwav": "",
  "Dm_RT_0039_Text_003_d.bwav": "",
  "Dm_RT_0039_Text_004_b.bwav": "真的是你！",
  "Dm_RT_0039_Text_005_b.bwav": "林克！",
  "Dm_SK_0003_Text_000_ab.bwav": "林克……",
  "Dm_SK_0003_Text_000_b.bwav": "林克……",
  "Dm_SK_0003_Text_001_b.bwav": "你的剑，大师之剑……",
  "Dm_SK_0003_Text_002_b.bwav": "是消灭魔王唯一的力量。",
  "Dm_SK_0003_Text_003_b.bwav": "虽然败给了魔王一次……",
  "Dm_SK_0003_Text_004_b.bwav": "但长久的休眠将治愈重伤，",
  "Dm_SK_0003_Text_005_b.bwav": "为了你这次能够战胜魔王，",
  "Dm_SK_0003_Text_006_b.bwav": "……我一定会为它注入新的力量。",
  "Dm_SK_0003_Text_007_c.bwav": "你是我们最后的希望……",
  "Dm_SK_0003_Text_008_b.bwav": "我衷心祈愿……",
  "Dm_SK_0003_Text_009_b.bwav": "这把剑能交到未来的你手中……",
  "Dm_ZE_0004_Text_000_b.bwav": "果然……",
  "Dm_ZE_0004_Text_001_b.bwav": "这里不是我所熟悉的地方。",
  "Dm_ZE_0004_Text_002_b.bwav": "而是作为神话流传的，遥远的过去……",
  "Dm_ZE_0004_Text_003_c.bwav": "真的是海拉鲁建国的时代啊……",
  "Dm_ZE_0004_Text_005_ab.bwav": "我们也很惊讶，塞尔达阁下。",
  "Dm_ZE_0004_Text_005_b.bwav": "但是，你拥有和索尼娅相同的司掌时间的秘石，我信任你。",
  "Dm_ZE_0004_Text_005_c.bwav": "",
  "Dm_ZE_0004_Text_006_b.bwav": "哎呀，就算她没有秘石，我也会很快相信的，\n劳鲁。",
  "Dm_ZE_0004_Text_007_b.bwav": "我能从她身上感受到我的力量，还有你的光之力……",
  "Dm_ZE_0004_Text_008_b.bwav": "最重要的是，还能感受到相同的血脉。",
  "Dm_ZE_0004_Text_008_c.bwav": "",
  "Dm_ZE_0004_Text_009_b.bwav": "的确如此。",
  "Dm_ZE_0004_Text_010_b.bwav": "那么，塞尔达阁下，",
  "Dm_ZE_0004_Text_011_bb.bwav": "你刚才也说了……\n你必须尽快回到原来的时代。",
  "Dm_ZE_0004_Text_012_c.bwav": "是的……",
  "Dm_ZE_0004_Text_013_b.bwav": "在我的时代，发生了非常糟糕的事情……",
  "Dm_ZE_0004_Text_014_bab.bwav": "我必须尽快回去，\n但是，我不知道方法……",
  "Dm_ZE_0004_Text_014_bac.bwav": "就连我是怎么来到这个时代的，\n我也完全不清楚……",
  "Dm_ZE_0004_Text_014_bb.bwav": "",
  "Dm_ZE_0004_Text_014_c.bwav": "",
  "Dm_ZE_0004_Text_015_b.bwav": "",
  "Dm_ZE_0004_Text_016_b.bwav": "我说，塞尔达小姐。",
  "Dm_ZE_0004_Text_016_c.bwav": "",
  "Dm_ZE_0004_Text_017_b.bwav": "总之我们先冷静下来吧，\n你可以留在我们的城堡里。",
  "Dm_ZE_0004_Text_018_b.bwav": "不……这样的话……",
  "Dm_ZE_0004_Text_019_b.bwav": "我会把你当作我的远亲介绍给大家的。",
  "Dm_ZE_0004_Text_020_c.bwav": "毕竟这也不算是说谎嘛。",
  "Dm_ZE_0004_Text_021_b.bwav": "替换的衣服也准备一下吧。",
  "Dm_ZE_0004_Text_021_c.bwav": "",
  "Dm_ZE_0004_Text_022_b.bwav": "只要慢慢思考，答案自然会浮现的。",
  "Dm_ZE_0004_Text_023_ab.bwav": "",
  "Dm_ZE_0004_Text_023_b.bwav": "非常感谢……",
  "Dm_ZE_0004_Text_024_c.bwav": "对了……",
  "Dm_ZE_0004_Text_025_c.bwav": "米涅鲁也许对穿越时间的方法有些头绪。",
  "Dm_ZE_0004_Text_026_c.bwav": "米涅鲁……？",
  "Dm_ZE_0004_Text_027_c.bwav": "没错……\n她比谁都了解左纳乌的智慧……",
  "Dm_ZE_0004_Text_029_b.bwav": "也和我们一样，拥有秘石……\n她是我的姐姐。",
  "Dm_ZE_0005_Text_000_b.bwav": "",
  "Dm_ZE_0005_Text_001_b.bwav": "你没事吧？\n好像有点儿心不在焉啊？",
  "Dm_ZE_0005_Text_002_b.bwav": "不好意思，\n我在想怎样才能回到原来的时代。",
  "Dm_ZE_0005_Text_003_b.bwav": "如果能像索尼娅大人那样熟练使用时之力……",
  "Dm_ZE_0005_Text_004_b.bwav": "我应该就能更进一步了……",
  "Dm_ZE_0005_Text_005_b.bwav": "是啊……",
  "Dm_ZE_0005_Text_006_b.bwav": "要说诀窍的话，应该是把对事物的记忆想象出来吧。",
  "Dm_ZE_0005_Text_007_b.bwav": "自己在何时何地做什么事，\n把它想象出来，然后尝试回到原来的地方……",
  "Dm_ZE_0005_Text_010_ab.bwav": "",
  "Dm_ZE_0005_Text_010_b.bwav": "对事物的记忆……",
  "Dm_ZE_0005_Text_011_b.bwav": "没事的，\n你一定能掌握这份力量，找到回去的方法的。",
  "Dm_ZE_0005_Text_012_b.bwav": "……但是，塞尔达，\n你的烦恼应该不止这一件吧？",
  "Dm_ZE_0005_Text_013_b.bwav": "",
  "Dm_ZE_0005_Text_014_b.bwav": "你想赶快回到原来的时代，",
  "Dm_ZE_0005_Text_015_b.bwav": "但是也想为这个时代尽一份力……\n没错吧？",
  "Dm_ZE_0005_Text_016_ab.bwav": "",
  "Dm_ZE_0005_Text_016_b.bwav": "您为什么会……！",
  "Dm_ZE_0005_Text_017_b.bwav": "",
  "Dm_ZE_0005_Text_017_c.bwav": "",
  "Dm_ZE_0005_Text_018_b.bwav": "因为没什么事能瞒住索尼娅嘛。",
  "Dm_ZE_0005_Text_019_b.bwav": "谢谢你为我们担心，塞尔达。",
  "Dm_ZE_0005_Text_020_b.bwav": "但是，你只要关心自己的时代就好了。",
  "Dm_ZE_0005_Text_021_b.bwav": "你拥有的不只是时之力，还有强大而神圣的破魔之力。",
  "Dm_ZE_0005_Text_022_b.bwav": "这份力量必须用于保护原来的时代。",
  "Dm_ZE_0005_Text_023_b.bwav": "索尼娅大人……",
  "Dm_ZE_0005_Text_024_b.bwav": "你必须平安回去，让林克先生也放心才行。",
  "Dm_ZE_0005_Text_025_b.bwav": "林克？",
  "Dm_ZE_0005_Text_025_c.bwav": "",
  "Dm_ZE_0005_Text_026_b.bwav": "我还是第一次听说这个名字啊。",
  "Dm_ZE_0005_Text_027_b.bwav": "他是在我的时代，拯救了海拉鲁王国和我的勇者。",
  "Dm_ZE_0005_Text_028_b.bwav": "虽然他原本只是我的护卫，一名近卫骑士……",
  "Dm_ZE_0005_Text_029_b.bwav": "哦，勇者啊。",
  "Dm_ZE_0005_Text_030_b.bwav": "他每天都勤于训练，不论多么绝望的状况都勇于面对……",
  "Dm_ZE_0005_Text_031_b.bwav": "没错……",
  "Dm_ZE_0005_Text_032_b.bwav": "他很强大……",
  "Dm_ZE_0005_Text_032_c.bwav": "",
  "Dm_ZE_0005_Text_033_b.bwav": "是个内心坚强的人……",
  "Dm_ZE_0005_Text_034_c.bwav": "看来你很信任他啊。",
  "Dm_ZE_0005_Text_035_c.bwav": "能被塞尔达如此夸奖的人，我还真想见他一面啊。",
  "Dm_ZE_0005_Text_036_b.bwav": "是啊。",
  "Dm_ZE_0005_Text_037_b.bwav": "我也想见见他呢。",
  "Dm_ZE_0005_Text_038_b.bwav": "一定是一名威风凛然的骑士吧。",
  "Dm_ZE_0005_Text_039_b.bwav": "毕竟塞尔达都这么评价他了。",
  "Dm_ZE_0005_Text_040_b.bwav": "",
  "Dm_ZE_0005_Text_041_b.bwav": "",
  "Dm_ZE_0006_Text_000_b.bwav": "总之我先看了一下……",
  "Dm_ZE_0006_Text_001_b.bwav": "这的确不是这个时代的技术产物。",
  "Dm_ZE_0006_Text_002_c.bwav": "但是传送的功能\n或许在这里也可以使用。",
  "Dm_ZE_0006_Text_003_b.bwav": "我想稍微调试一下，\n能把它借我一用吗？",
  "Dm_ZE_0006_Text_004_c.bwav": "好的，米涅鲁大人。\n如果能帮到您的忙就好了。",
  "Dm_ZE_0006_Text_005_b.bwav": "那我就先借用了。",
  "Dm_ZE_0006_Text_006_c.bwav": "您相信我来自未来吗……？",
  "Dm_ZE_0006_Text_007_b.bwav": "我从一开始就没有怀疑过你。",
  "Dm_ZE_0006_Text_008_c.bwav": "你有办法让塞尔达阁下回到原来的时代吗，姐姐？",
  "Dm_ZE_0006_Text_009_c.bwav": "你穿越时间来到这里，\n多半是因为秘石的力量吧。",
  "Dm_ZE_0006_Text_010_b.bwav": "而且秘石本身是使持有者力量倍增的秘宝。",
  "Dm_ZE_0006_Text_011_b.bwav": "我的话是能让灵魂出窍的魂之力。",
  "Dm_ZE_0006_Text_012_b.bwav": "劳鲁则是灭魔的光之力。",
  "Dm_ZE_0006_Text_013_b.bwav": "索尼娅是司掌时间的时之力……",
  "Dm_ZE_0006_Text_014_b.bwav": "我从你的身上能感觉到“光”与“时”两种力量……",
  "Dm_ZE_0006_Text_014_d.bwav": "",
  "Dm_ZE_0006_Text_015_b.bwav": "不过倍增的似乎只有时之力……",
  "Dm_ZE_0006_Text_016_c.bwav": "时之力……",
  "Dm_ZE_0006_Text_017_b.bwav": "但是，秘石的作用说到底也只是使力量倍增。",
  "Dm_ZE_0006_Text_018_b.bwav": "实际上去控制并使用这份力量的还是你自己。",
  "Dm_ZE_0006_Text_019_b.bwav": "所以，如果你不知道回去的方法……",
  "Dm_ZE_0006_Text_020_c.bwav": "",
  "Dm_ZE_0006_Text_022_c.bwav": "……关于秘石的传说中，\n有一个叫作“龙化之法”的禁忌之术。",
  "Dm_ZE_0006_Text_023_b.bwav": "“吞下秘石之人将化为长生不老的龙。”",
  "Dm_ZE_0006_Text_024_b.bwav": "“由此获得永恒的时间……”",
  "Dm_ZE_0006_Text_024_d.bwav": "",
  "Dm_ZE_0006_Text_025_c.bwav": "……原来如此。\n某种意义上来说，的确是超越时间之术。",
  "Dm_ZE_0006_Text_026_b.bwav": "你的意思是，这个传说能成为什么线索吗？",
  "Dm_ZE_0006_Text_027_b.bwav": "没错。",
  "Dm_ZE_0006_Text_028_b.bwav": "不过，这个传说还有后续。",
  "Dm_ZE_0006_Text_029_b.bwav": "“化身为龙之人的心将永不复还……”",
  "Dm_ZE_0006_Text_030_c.bwav": "这就是被称为“禁忌之术”的原因。",
  "Dm_ZE_0006_Text_031_b.bwav": "虽然在超越时间这一点上也许能成为突破口，",
  "Dm_ZE_0006_Text_032_b.bwav": "但是永远失去自我就本末倒置了。",
  "Dm_ZE_0006_Text_033_b.bwav": "不好意思，我也帮不上忙。",
  "Dm_ZE_0006_Text_033_c.bwav": "",
  "Dm_ZE_0006_Text_034_b.bwav": "回到起点了啊……",
  "Dm_ZE_0006_Text_034_cb.bwav": "",
  "Dm_ZE_0006_Text_035_b.bwav": "话虽如此，如果塞尔达阁下能对力量深入理解，\n或许会有新的发现。",
  "Dm_ZE_0006_Text_036_b.bwav": "使用力量的方法就去向索尼娅学习吧？",
  "Dm_ZE_0006_Text_036_d.bwav": "",
  "Dm_ZE_0006_Text_038_b.bwav": "……我明白了！",
  "Dm_ZE_0007_Text_000_b.bwav": "劳鲁陛下，",
  "Dm_ZE_0007_Text_001_b.bwav": "刚才的报告……\n说是格鲁德沙漠最后的村子也已经被攻陷。",
  "Dm_ZE_0007_Text_001_bb.bwav": "",
  "Dm_ZE_0007_Text_001_c.bwav": "",
  "Dm_ZE_0007_Text_002_ab.bwav": "",
  "Dm_ZE_0007_Text_002_b.bwav": "这样下去就抵御不住魔王军的侵略了。",
  "Dm_ZE_0007_Text_003_b.bwav": "……我明白。",
  "Dm_ZE_0007_Text_004_b.bwav": "我会阻止身为元凶的魔王。",
  "Dm_ZE_0007_Text_005_b.bwav": "劳鲁，",
  "Dm_ZE_0007_Text_006_b.bwav": "现在的魔王，已经无法由你一人来阻止了。",
  "Dm_ZE_0007_Text_007_b.bwav": "",
  "Dm_ZE_0007_Text_008_b.bwav": "但是你并不是孤身一人。",
  "Dm_ZE_0007_Text_009_b.bwav": "你的身边有格鲁德、鼓隆、卓拉、利特的族长，还有塞尔达……",
  "Dm_ZE_0007_Text_009_baaab.bwav": "",
  "Dm_ZE_0007_Text_009_baab.bwav": "",
  "Dm_ZE_0007_Text_009_bab.bwav": "",
  "Dm_ZE_0007_Text_009_bb.bwav": "",
  "Dm_ZE_0007_Text_009_c.bwav": "",
  "Dm_ZE_0007_Text_010_b.bwav": "当然，我也会与你并肩作战……",
  "Dm_ZE_0007_Text_011_ab.bwav": "",
  "Dm_ZE_0007_Text_011_b.bwav": "",
  "Dm_ZE_0007_Text_012_c.bwav": "我有件东西想给大家看一看……",
  "Dm_ZE_0007_Text_013_b.bwav": "这是左纳乌的……",
  "Dm_ZE_0007_Text_014_b.bwav": "秘石……",
  "Dm_ZE_0007_Text_015_ab.bwav": "",
  "Dm_ZE_0007_Text_015_c.bwav": "请大家借与我力量。",
  "Dm_ZE_0007_Text_022_c.bwav": "",
  "Dm_ZE_0007_Text_023_b.bwav": "",
  "Dm_ZE_0007_Text_024_b.bwav": "",
  "Dm_ZE_0007_Text_025_b.bwav": "",
  "Dm_ZE_0007_Text_026_b.bwav": "",
  "Dm_ZE_0007_Text_027_b.bwav": "",
  "Dm_ZE_0007_Text_027_c.bwav": "吾等",
  "Dm_ZE_0007_Text_028_b.bwav": "",
  "Dm_ZE_0007_Text_029_b.bwav": "",
  "Dm_ZE_0007_Text_030_b.bwav": "",
  "Dm_ZE_0007_Text_031_b.bwav": "",
  "Dm_ZE_0007_Text_032_b.bwav": "",
  "Dm_ZE_0007_Text_033_b.bwav": "",
  "Dm_ZE_0007_Text_033_c.bwav": "集结",
  "Dm_ZE_0007_Text_034_b.bwav": "",
  "Dm_ZE_0007_Text_035_b.bwav": "",
  "Dm_ZE_0007_Text_036_b.bwav": "",
  "Dm_ZE_0007_Text_037_b.bwav": "",
  "Dm_ZE_0007_Text_038_b.bwav": "",
  "Dm_ZE_0007_Text_039_b.bwav": "",
  "Dm_ZE_0007_Text_039_c.bwav": "于此，",
  "Dm_ZE_0007_Text_040_b.bwav": "",
  "Dm_ZE_0007_Text_041_b.bwav": "",
  "Dm_ZE_0007_Text_042_b.bwav": "",
  "Dm_ZE_0007_Text_043_b.bwav": "",
  "Dm_ZE_0007_Text_044_b.bwav": "",
  "Dm_ZE_0007_Text_045_b.bwav": "",
  "Dm_ZE_0007_Text_046_b.bwav": "发誓将协助光之王完成讨伐魔王的大业。",
  "Dm_ZE_0008_Text_000_c.bwav": "索尼娅……",
  "Dm_ZE_0008_Text_001_c.bwav": "是塞尔达啊……",
  "Dm_ZE_0008_Text_002_c.bwav": "劳鲁大人……\n在明天和魔王决战之前，我有件事要说……",
  "Dm_ZE_0008_Text_003_c.bwav": "我之所以能来到这个时代，\n是因为一个沉睡在地下的男人……",
  "Dm_ZE_0008_Text_004_b.bwav": "……嗯。",
  "Dm_ZE_0008_Text_005_b.bwav": "你继续说。",
  "Dm_ZE_0008_Text_006_d.bwav": "……当我看到因秘石而样貌改变的加侬多夫时，\n我明确了一件事。",
  "Dm_ZE_0008_Text_007_c.bwav": "那就是，在地下从长眠中苏醒的人就是他！",
  "Dm_ZE_0008_Text_008_c.bwav": "那个男人……并没有被打倒……",
  "Dm_ZE_0008_Text_009_d.bwav": "甚至，他还一直活到了我所在的时代！！",
  "Dm_ZE_0008_Text_010_c.bwav": "明天的战斗……",
  "Dm_ZE_0008_Text_011_bb.bwav": "出动剩余全部兵力与魔王加侬多夫决战，\n也一定无法将他打倒！",
  "Dm_ZE_0008_Text_012_ac.bwav": "",
  "Dm_ZE_0008_Text_012_c.bwav": "而劳鲁大人您……",
  "Dm_ZE_0008_Text_013_c.bwav": "……即便如此，",
  "Dm_ZE_0008_Text_014_c.bwav": "我也必须出面战斗。",
  "Dm_ZE_0008_Text_015_b.bwav": "",
  "Dm_ZE_0008_Text_017_c.bwav": "他是因我的傲慢而孕育出的怪物……",
  "Dm_ZE_0008_Text_018_c.bwav": "我必须亲自为此赎罪。",
  "Dm_ZE_0008_Text_019_c.bwav": "更何况……",
  "Dm_ZE_0008_Text_020_c.bwav": "我是海拉鲁的国王。\n国王有保护臣民和国土的义务。",
  "Dm_ZE_0008_Text_021_c.bwav": "即使拼上我这条命……",
  "Dm_ZE_0008_Text_022_ab.bwav": "",
  "Dm_ZE_0008_Text_022_b.bwav": "劳鲁大人……",
  "Dm_ZE_0008_Text_023_c.bwav": "如果我们无法打倒那个男人……",
  "Dm_ZE_0008_Text_024_c.bwav": "你所说的……持有驱魔之剑的剑士，",
  "Dm_ZE_0008_Text_025_c.bwav": "也就是林克阁下，我会将一切都托付给他。",
  "Dm_ZE_0008_Text_026_ab.bwav": "",
  "Dm_ZE_0008_Text_026_c.bwav": "但你口中的，是你没在这个世界出现过的未来……\n而现在，你就在这里。",
  "Dm_ZE_0008_Text_027_c.bwav": "塞尔达……我相信你来到这个世界这件事\n一定具有某种意义……",
  "Dm_ZE_0008_Text_028_b.bwav": "我来到这里的……意义……",
  "Dm_ZE_0010_Text_001_c.bwav": "总算把他给封印住了，可是……",
  "Dm_ZE_0010_Text_002_ab.bwav": "林克……\n这样下去，即便是你也无法战胜他……",
  "Dm_ZE_0010_Text_002_bb.bwav": "",
  "Dm_ZE_0010_Text_004_bb.bwav": "",
  "Dm_ZE_0010_Text_004_c.bwav": "",
  "Dm_ZE_0010_Text_005_b.bwav": "",
  "Dm_ZE_0010_Text_006_bb.bwav": "大师……之剑！？",
  "Dm_ZE_0010_Text_006_c.bwav": "",
  "Dm_ZE_0010_Text_007_b.bwav": "为什么大师之剑会在这里……",
  "Dm_ZE_0010_Text_007_c.bwav": "",
  "Dm_ZE_0010_Text_008_bb.bwav": "林克应该……平安无事吧？",
  "Dm_ZE_0010_Text_008_c.bwav": "你为了复活……穿越时间来到了我的身边……",
  "Dm_ZE_0010_Text_009_c.bwav": "",
  "Dm_ZE_0010_Text_009_d.bwav": "塞尔达……我相信你来到这个世界这件事\n一定具有某种意义……",
  "Dm_ZE_0010_Text_010_aaac.bwav": "我还有力所能及的事情……",
  "Dm_ZE_0010_Text_010_aabb.bwav": "不……这件事只有我能做到……",
  "Dm_ZE_0010_Text_010_aabc.bwav": "就是“打倒那个男人”。",
  "Dm_ZE_0010_Text_010_aac.bwav": "",
  "Dm_ZE_0010_Text_010_aad.bwav": "“化身为龙之人的心将永不复还……”",
  "Dm_ZE_0010_Text_010_aae.bwav": "无法……再恢复为人……",
  "Dm_ZE_0010_Text_010_aaf.bwav": "",
  "Dm_ZE_0010_Text_012_c.bwav": "林克……",
  "Dm_ZE_0010_Text_014_b.bwav": "来寻找我吧……",
  "Dm_ZE_0011_Text_000_b.bwav": "……那就是驱魔之剑？\n为我瘴气所破之刃，一无是处。",
  "Dm_ZE_0011_Text_001_b.bwav": "沐浴在神圣之力下，会让这把剑愈发强大……\n神圣之力越强，剑的力量越强……",
  "Dm_ZE_0011_Text_002_b.bwav": "你拥有的不只是时之力，还有强大而神圣的破魔之力。",
  "Dm_ZE_0011_Text_003_b.bwav": "“吞下秘石之人将化为长生不老的龙。”",
  "Dm_ZE_0011_Text_004_b.bwav": "“由此获得永恒的时间……”",
  "Dm_ZE_0011_Text_005_b.bwav": "米涅鲁大人……\n拜托你了……",
  "Dm_ZE_0011_Text_006_b.bwav": "林克……\n我一定会让大师之剑复活的。",
  "Dm_ZE_0011_Text_007_b.bwav": "直到未来将其交予你的那一刻为止，",
  "Dm_ZE_0011_Text_008_b.bwav": "我将持续注入神圣之力……\n一定会……让它成为足以打倒魔王的剑……！",
  "Dm_ZE_0011_Text_009_b.bwav": "“化身为龙之人的心将永不复还……”",
  "Dm_ZE_0011_Text_010_b.bwav": "",
  "Dm_ZE_0011_Text_011_b.bwav": "所以……",
  "Dm_ZE_0011_Text_012_b.bwav": "",
  "Dm_ZE_0011_Text_014_b.bwav": "",
  "Dm_ZE_0011_Text_015_b.bwav": "",
  "Dm_ZE_0011_Text_017_d.bwav": "",
  "Dm_ZE_0011_Text_018_b.bwav": "",
  "Dm_ZE_0011_Text_019_b.bwav": "",
  "Dm_ZE_0011_Text_020_b.bwav": "林克……！",
  "Dm_ZE_0011_Text_021_ab.bwav": "",
  "Dm_ZE_0011_Text_021_b.bwav": "守护这个世界吧……！！",
  "Dm_ZN_0009_Text_001_c.bwav": "林克……守护塞尔达之骑士啊……",
  "Dm_ZN_0009_Text_003_b.bwav": "请把它带到光芒指引之处……",
  "Dm_ZN_0013_Text_002_b.bwav": "林克……",
  "Dm_ZN_0013_Text_003_b.bwav": "守护塞尔达之骑士……",
  "Dm_ZN_0013_Text_005_b.bwav": "我们……要尽快……\n必须尽快相遇才行……",
  "Dm_ZN_0015_Text_022_b.bwav": "林克……\n守护塞尔达之骑士……",
  "Dm_ZN_0015_Text_023_b.bwav": "我乃魂之贤者，\n名为米涅鲁。",
  "Dm_ZN_0015_Text_024_b.bwav": "多亏你来到此地，\n我才终于得以与你交谈。",
  "Dm_ZN_0015_Text_025_b.bwav": "我如今只余灵魂存在……",
  "Dm_ZN_0015_Text_026_b.bwav": "若没有新的附身之躯，\n我便无法真正地与你见面。",
  "Dm_ZN_0015_Text_027_b.bwav": "从此处可以望见四处仓库……",
  "Dm_ZN_0015_Text_028_b.bwav": "请你前往每一处仓库，\n为我铸造附身之躯。",
  "Dm_ZN_0015_Text_029_b.bwav": "拜托你了，林克，\n守护塞尔达之骑士……",
  "Dm_ZN_0016_Text_005_c.bwav": "这是第1个……\n剩下3个也拜托你了，林克……",
  "Dm_ZN_0016_Text_006_c.bwav": "又收集到了1个零件，\n还剩下2个……",
  "Dm_ZN_0016_Text_007_c.bwav": "还剩1个，林克……\n附身之躯即将完成……",
  "Dm_ZN_0022_Text_006_b.bwav": "感谢你，林克。",
  "Dm_ZN_0022_Text_007_b.bwav": "最后需要的只剩一样东西了。",
  "Dm_ZN_0022_Text_008_b.bwav": "那就是……我的魂之秘石。",
  "Dm_ZN_0022_Text_009_b.bwav": "秘石就在这个地方，\n请把我带去这里。",
  "Dm_ZN_0022_Text_011_b.bwav": "一路上十分危险……",
  "Dm_ZN_0022_Text_012_b.bwav": "你为我铸就的这副附身之躯……\n这魔像中蕴藏着神秘的力量……",
  "Dm_ZN_0022_Text_013_b.bwav": "只要到了那里，你就会明白……",
  "Dm_ZN_0022_Text_014_b.bwav": "请你将我带到\n秘石所在之处吧。",
  "Dm_ZN_0030_Text_000_b.bwav": "我既是高傲的左纳乌族，也是魂之贤者……",
  "Dm_ZN_0030_Text_001_c.bwav": "而且……还是知晓塞尔达的夙愿，能助你一臂之力之人。",
  "Dm_ZN_0030_Text_002_b.bwav": "……米涅鲁。",
  "Dm_ZN_0030_Text_003_b.bwav": "……我终于见到你了，林克。",
  "Dm_ZN_0030_Text_004_d.bwav": "谢谢你。",
  "Dm_ZN_0030_Text_005_d.bwav": "多亏了你，才能夺回秘石。",
  "Dm_ZN_0030_Text_005_e.bwav": "本来的话，当你得到普尔亚平板的同时，\n我也应该苏醒了……",
  "Dm_ZN_0030_Text_005_f.bwav": "但是我的计划被妨碍，\n本来打算寄宿的魔像被魔王提前一步占领了。",
  "Dm_ZN_0030_Text_005_g.bwav": "而你凭借自己的力量找到了我……",
  "Dm_ZN_0030_Text_006_b.bwav": "林克……伸出手来。",
  "Dm_ZN_0030_Text_007_b.bwav": "我以魂之贤者——米涅鲁之名，将力量授予你。",
  "Dm_ZN_0030_Text_008_c.bwav": "好了……收下这份力量吧……",
  "Dm_ZN_0030_Text_009_c.bwav": "我和你有着深厚的缘分。",
  "Dm_ZN_0030_Text_012_b.bwav": "从今往后，我的灵魂将寄宿于那个魔像，\n成为你的力量。",
  "Dm_ZN_0032_Text_000_b.bwav": "在遥远的过去……神明的后裔左纳乌族\n带着伟大的智慧，降临到了地上。",
  "Dm_ZN_0032_Text_001_b.bwav": "他们带着神明的遗产……\n能使持有者力量倍增的秘宝——秘石。",
  "Dm_ZN_0032_Text_002_b.bwav": "我的弟弟劳鲁使用左纳乌的方法引导百姓，\n并与在地上邂逅的姑娘——索尼娅缔结了婚姻。",
  "Dm_ZN_0032_Text_003_b.bwav": "劳鲁将一颗秘石赠予了索尼娅……\n然后两人在大地上建立了一个国家。",
  "Dm_ZN_0032_Text_004_b.bwav": "劳鲁为国王，索尼娅为王后，其国家名则为海拉鲁。\n两人与众多的百姓一同奠定了繁荣的基础。",
  "Dm_ZN_0032_Text_005_b.bwav": "但是，悲剧却突然到来了……",
  "Dm_ZN_0032_Text_006_b.bwav": "出现于沙漠的邪恶之人……",
  "Dm_ZN_0032_Text_006_c.bwav": "格鲁德的首领——加侬多夫夺走了索尼娅的生命，\n并得到了她的秘石。",
  "Dm_ZN_0032_Text_007_c.bwav": "加侬多夫使用秘石的力量，从人变为了魔王，",
  "Dm_ZN_0032_Text_007_d.bwav": "孕育出大量怪物，开始袭击这个世界……",
  "Dm_ZN_0032_Text_008_b.bwav": "海拉鲁王国的人们与袭来的怪物拼命战斗，\n但还是敌不过邪恶之力，陷入了窘境……",
  "Dm_ZN_0032_Text_009_b.bwav": "劳鲁为了打破这现状，想到了一个策略。",
  "Dm_ZN_0032_Text_010_b.bwav": "他打算将秘石交予有力的战士，\n并与成为贤者的他们一起打倒魔王加侬多夫……",
  "Dm_ZN_0032_Text_011_b.bwav": "劳鲁他们本应能以人数优势讨伐魔王，",
  "Dm_ZN_0032_Text_012_b.bwav": "但是……",
  "Dm_ZN_0033_Text_000_b.bwav": "魔王的力量远超想象。",
  "Dm_ZN_0033_Text_001_b.bwav": "我在魔王的猛攻之下落败……",
  "Dm_ZN_0033_Text_002_b.bwav": "说我们毫无胜算也不为过。",
  "Dm_ZN_0033_Text_003_aaaab.bwav": "",
  "Dm_ZN_0033_Text_003_aaab.bwav": "",
  "Dm_ZN_0033_Text_003_aab.bwav": "",
  "Dm_ZN_0033_Text_003_ab.bwav": "",
  "Dm_ZN_0033_Text_003_b.bwav": "然后劳鲁他……",
  "Dm_ZN_0033_Text_004_b.bwav": "",
  "Dm_ZN_0033_Text_004_c.bwav": "",
  "Dm_ZN_0033_Text_005_ab.bwav": "",
  "Dm_ZN_0033_Text_005_b.bwav": "……决定使用最后的手段。",
  "Dm_ZN_0033_Text_005_c.bwav": "",
  "Dm_ZN_0033_Text_005_d.bwav": "",
  "Dm_ZN_0033_Text_005_e.bwav": "",
  "Dm_ZN_0033_Text_005_f.bwav": "",
  "Dm_ZN_0033_Text_005_g.bwav": "",
  "Dm_ZN_0033_Text_009_c.bwav": "",
  "Dm_ZN_0033_Text_010_aaaab.bwav": "",
  "Dm_ZN_0033_Text_010_aaab.bwav": "",
  "Dm_ZN_0033_Text_010_aab.bwav": "",
  "Dm_ZN_0033_Text_010_ab.bwav": "",
  "Dm_ZN_0033_Text_010_b.bwav": "",
  "Dm_ZN_0033_Text_011_b.bwav": "",
  "Dm_ZN_0033_Text_012_b.bwav": "",
  "Dm_ZN_0033_Text_013_b.bwav": "",
  "Dm_ZN_0033_Text_014_b.bwav": "",
  "Dm_ZN_0033_Text_015_b.bwav": "我已经见过你这招了！！",
  "Dm_ZN_0033_Text_016_c.bwav": "结束了，",
  "Dm_ZN_0033_Text_017_c.bwav": "劳鲁！",
  "Dm_ZN_0033_Text_018_c.bwav": "",
  "Dm_ZN_0033_Text_019_bb.bwav": "你的自大会让你丧命的，加侬多夫。",
  "Dm_ZN_0033_Text_019_c.bwav": "",
  "Dm_ZN_0033_Text_020_b.bwav": "",
  "Dm_ZN_0033_Text_021_c.bwav": "",
  "Dm_ZN_0033_Text_022_aaaaaaab.bwav": "",
  "Dm_ZN_0033_Text_022_abab.bwav": "",
  "Dm_ZN_0033_Text_022_abac.bwav": "",
  "Dm_ZN_0033_Text_022_ac.bwav": "",
  "Dm_ZN_0033_Text_022_b.bwav": "束缚我的心脏，夺走我的魔力，\n……你是打算将我封印吗？",
  "Dm_ZN_0033_Text_023_b.bwav": "这种耍小聪明的招式可真适合你啊。",
  "Dm_ZN_0033_Text_024_b.bwav": "这样你可就没有退路了。",
  "Dm_ZN_0033_Text_025_c.bwav": "可别小看我了……",
  "Dm_ZN_0033_Text_026_c.bwav": "我从一开始就没打算全身而退……",
  "Dm_ZN_0033_Text_027_b.bwav": "",
  "Dm_ZN_0033_Text_028_b.bwav": "……劳鲁大人！",
  "Dm_ZN_0033_Text_029_b.bwav": "",
  "Dm_ZN_0033_Text_030_b.bwav": "对我来说万年如一瞬，\n你这么做只是徒劳。",
  "Dm_ZN_0033_Text_031_c.bwav": "你错了。",
  "Dm_ZN_0033_Text_032_c.bwav": "在遥远的未来……一定会出现能将你讨伐之人。",
  "Dm_ZN_0033_Text_033_c.bwav": "持有驱魔之剑的剑士……林克。",
  "Dm_ZN_0033_Text_034_c.bwav": "你可别忘了这个名字。",
  "Dm_ZN_0033_Text_035_b.bwav": "林克？",
  "Dm_ZN_0033_Text_036_b.bwav": "……真有趣。\n……我会好好……期待的……",
  "Dm_ZN_0039_Text_000_c.bwav": "你的意思是，这把剑和你一样是穿越时间而来的……？",
  "Dm_ZN_0039_Text_001_c.bwav": "是的，我在原来的时代见过这把剑。",
  "Dm_ZN_0039_Text_001_d.bwav": "这把大师之剑，即使破损不堪，\n也能使魔王负伤……",
  "Dm_ZN_0039_Text_002_c.bwav": "你是说那个让我们无计可施的魔王……？",
  "Dm_ZN_0039_Text_003_c.bwav": "",
  "Dm_ZN_0039_Text_004_c.bwav": "但是，你拿这把剑打算做什么？",
  "Dm_ZN_0039_Text_005_c.bwav": "如果大师之剑持续充盈神圣之力，\n它将会再生为一把更加强韧的剑。",
  "Dm_ZN_0039_Text_005_d.bwav": "确实……如果这把剑能够再生和强化，\n或许能成为对付魔王的王牌。",
  "Dm_ZN_0039_Text_005_e.bwav": "但是，想要为这把剑供给足够对抗魔王的力量，\n会花费很长的时间。",
  "Dm_ZN_0039_Text_005_f.bwav": "要在如此漫无止境的时间里，\n使剑一直充盈神圣之力，究竟要怎么做？",
  "Dm_ZN_0039_Text_007_c.bwav": "方法是有的……",
  "Dm_ZN_0039_Text_008_c.bwav": "",
  "Dm_ZN_0039_Text_010_c.bwav": "难道说……",
  "Dm_ZN_0039_Text_011_aab.bwav": "……没错，\n我要使用那个法术……！",
  "Dm_ZN_0039_Text_011_c.bwav": "我告诫过你了！",
  "Dm_ZN_0039_Text_011_d.bwav": "那是禁忌之术……使用它就等于放弃为人了！\n难道你……！",
  "Dm_ZN_0039_Text_011_e.bwav": "",
  "Dm_ZN_0039_Text_013_bb.bwav": "",
  "Dm_ZN_0039_Text_013_c.bwav": "米涅鲁大人！",
  "Dm_ZN_0039_Text_014_c.bwav": "",
  "Dm_ZN_0039_Text_015_c.bwav": "一旦使用……就再也无法恢复为人了……",
  "Dm_ZN_0039_Text_016_ab.bwav": "",
  "Dm_ZN_0039_Text_016_c.bwav": "当我将剑握在手里的时候，我就确信了，\n我就是为了这把剑才穿越时间来到这里的。",
  "Dm_ZN_0039_Text_017_c.bwav": "我……",
  "Dm_ZN_0039_Text_018_d.bwav": "我要复活大师之剑，把它交给林克！",
  "Dm_ZN_0039_Text_019_abb.bwav": "",
  "Dm_ZN_0039_Text_019_ac.bwav": "……我明白了。",
  "Dm_ZN_0039_Text_019_c.bwav": "你的决心……很坚定。",
  "Dm_ZN_0039_Text_020_ac.bwav": "",
  "Dm_ZN_0039_Text_020_c.bwav": "此番事件，说是因我们左纳乌的傲慢而起也不为过……",
  "Dm_ZN_0039_Text_021_c.bwav": "我会将我剩余生命……",
  "Dm_ZN_0039_Text_022_ab.bwav": "全部托付给你所说的勇者——林克阁下。",
  "Dm_ZN_0039_Text_022_ac.bwav": "就算我的肉体毁灭了，灵魂也会贯彻这个信念……",
  "Dm_ZN_0039_Text_023_ac.bwav": "",
  "Dm_ZN_0039_Text_024_b.bwav": "",
  "Dm_ZO_0016_Text_003_b.bwav": "",
  "Dm_ZO_0017_Text_016_c.bwav": "……里……",
  "Dm_ZO_0017_Text_017_c.bwav": "……来……",
  "Dm_ZO_0017_Text_018_c.bwav": "请来寻吾……",
  "Dm_ZO_0023_Text_000_b.bwav": "后代啊，吾之后代啊……",
  "Dm_ZO_0023_Text_000_c.bwav": "这里是卓拉的清水之源……",
  "Dm_ZO_0023_Text_001_b.bwav": "以汝之力，打开4处水栓，\n便可集水于此。",
  "Dm_ZO_0023_Text_002_b.bwav": "听吾指引……",
  "Dm_ZO_0024_01.bwav": "哦哦！\n这样水栓就打开了啊！\n很顺利卓！\n还剩下3处！",
  "Dm_ZO_0024_02.bwav": "漂亮卓！林克！\n再打开另外2处水栓就好……！",
  "Dm_ZO_0024_03.bwav": "好！\n就剩最后一处了，林克！",
  "Dm_ZO_0024_04.bwav": "干得漂亮，林克！",
  "Dm_ZO_0028_00_b.bwav": "好！这样一来水就全部注满了卓！\n再操作一次中央的水栓，林克！",
  "Dm_ZO_0030_Text_000_b.bwav": "",
  "Dm_ZO_0030_Text_002_b.bwav": "",
  "Dm_ZO_0032_Text_000_b.bwav": "事发之时距今已远。\n彼时海拉鲁王国于此地初建……",
  "Dm_ZO_0032_Text_001_b.bwav": "一穷凶极恶者现身于世，袭击无罪之人，欲使家国倾覆。\n此人即是魔王……",
  "Dm_ZO_0032_Text_002_b.bwav": "而初代海拉鲁国王劳鲁与六名战士挺身而出，\n决心与其对抗。",
  "Dm_ZO_0032_Text_003_b.bwav": "劳鲁交予吾等一物，\n以助吾等与魔王交战。",
  "Dm_ZO_0032_Text_004_b.bwav": "此物即秘石……\n是为倍增持有者力量之秘宝。",
  "Dm_ZO_0032_Text_004_c.bwav": "劳鲁交予吾等秘石，\n以助吾等与魔王交战。",
  "Dm_ZO_0032_Text_004_d.bwav": "此物乃倍增持有者力量之秘宝。",
  "Dm_ZO_0032_Text_005_b.bwav": "吾为六战士之一，乃水之贤者，\n亦携秘石与其交锋。",
  "Dm_ZO_0032_Text_006_b.bwav": "然，魔王强悍之甚……",
  "Dm_ZO_0032_Text_007_b.bwav": "其猛烈贯穿吾之水之加护，\n其灵敏令众人无不胆寒……",
  "Dm_ZO_0032_Text_009_c.bwav": "国王劳鲁遂醒悟，\n吾等并无击败魔王之力。",
  "Dm_ZO_0032_Text_010_b.bwav": "彼如此抉择——\n以一己之身封印魔王，换战争终结。",
  "Dm_ZO_0032_Text_011_b.bwav": "此乃“封印战争”……",
  "Dm_ZO_0032_Text_013_c.bwav": "吾等得以幸存，而后不久……\n一人寻至吾所，决定了吾等卓拉族之命运。",
  "Dm_ZO_0032_Text_014_c.bwav": "此人即六贤者之一——时之贤者。",
  "Dm_ZO_0032_Text_014_d.bwav": "而后不久……",
  "Dm_ZO_0032_Text_014_e.bwav": "六贤者之一——时之贤者寻至吾所，\n决定了吾等卓拉族之命运。",
  "Dm_ZO_0032_Text_016_c.bwav": "有朝一日，魔王的封印会解除，他会再次作乱……",
  "Dm_ZO_0032_Text_017_c.bwav": "到时候，剑士林克会需要\n与之对抗的力量……",
  "Dm_ZO_0032_Text_018_c.bwav": "拜托了，\n请司水的卓拉一族助他一臂之力。",
  "Dm_ZO_0032_Text_019_c.bwav": "此乃吾等使命确立之刹那……",
  "Dm_ZO_0032_Text_020_c.bwav": "讨伐魔王乃吾等誓愿。",
  "Dm_ZO_0032_Text_021_b.bwav": "待魔王复活之时，\n吾等卓拉一族将再次觉醒为水之贤者，",
  "Dm_ZO_0032_Text_022_b.bwav": "誓与剑士林克一同战斗。",
  "Dm_ZO_0033_Text_000_c.bwav": "此乃封印战争之悲剧，\n及吾等一族命运！",
  "Dm_ZO_0033_Text_001_b.bwav": "……汝等竭力拼搏，救卓拉领地于水火。\n然魔王复活之日将近。",
  "Dm_ZO_0033_Text_002_b.bwav": "吾之后代，希多。",
  "Dm_ZO_0033_Text_003_b.bwav": "请继承此秘石，\n履行吾与时之贤者所定之约……",
  "Dm_ZO_0033_Text_004_b.bwav": "发誓与剑士林克\n一同作战。",
  "SageOfGerudo_PyramidLiftConsole_00.bwav": "这就是蓄电池……\n看来我的雷电已经注入进去了。\n好，那就还剩3个了！",
  "SageOfGerudo_PyramidLiftConsole_01.bwav": "还剩下2个了，\n林克！一鼓作气吧！",
  "SageOfGerudo_PyramidLiftConsole_02.bwav": "好！\n这样就只剩1个蓄电池了！",
  "SageOfGerudo_PyramidLiftConsole_03.bwav": "好！\n所有蓄电池都已经注入雷电了。\n现在中央的机关应该就能启动了，\n我们走吧，林克！"
}
